{
  "id": 2001,
  "name": "Rio Grande do Sul",
  "state_code": "RS",
  "latitude": "-30.03463160",
  "longitude": "-51.21769860",
  "type": null,
  "cities": [
    {
      "id": 10075,
      "name": "Aceguá",
      "latitude": "-31.64597000",
      "longitude": "-54.10715000"
    },
    {
      "id": 15664,
      "name": "Água Santa",
      "latitude": "-28.18543000",
      "longitude": "-52.01286000"
    },
    {
      "id": 10097,
      "name": "Agudo",
      "latitude": "-29.62631000",
      "longitude": "-53.22404000"
    },
    {
      "id": 10106,
      "name": "Ajuricaba",
      "latitude": "-28.20723000",
      "longitude": "-53.74458000"
    },
    {
      "id": 10122,
      "name": "Alecrim",
      "latitude": "-27.65897000",
      "longitude": "-54.75943000"
    },
    {
      "id": 10124,
      "name": "Alegrete",
      "latitude": "-29.78306000",
      "longitude": "-55.79194000"
    },
    {
      "id": 10126,
      "name": "Alegria",
      "latitude": "-27.79967000",
      "longitude": "-54.05855000"
    },
    {
      "id": 10145,
      "name": "Almirante Tamandaré do Sul",
      "latitude": "-28.15104000",
      "longitude": "-52.91142000"
    },
    {
      "id": 10148,
      "name": "Alpestre",
      "latitude": "-27.22135000",
      "longitude": "-53.05749000"
    },
    {
      "id": 10161,
      "name": "Alto Alegre",
      "latitude": "-28.79752000",
      "longitude": "-52.98177000"
    },
    {
      "id": 10169,
      "name": "Alto Feliz",
      "latitude": "-29.36438000",
      "longitude": "-51.30068000"
    },
    {
      "id": 10195,
      "name": "Alvorada",
      "latitude": "-29.98897000",
      "longitude": "-51.03717000"
    },
    {
      "id": 10207,
      "name": "Amaral Ferrador",
      "latitude": "-30.80769000",
      "longitude": "-52.29964000"
    },
    {
      "id": 10215,
      "name": "Ametista do Sul",
      "latitude": "-27.36698000",
      "longitude": "-53.18701000"
    },
    {
      "id": 10248,
      "name": "André da Rocha",
      "latitude": "-28.58832000",
      "longitude": "-51.49976000"
    },
    {
      "id": 10267,
      "name": "Anta Gorda",
      "latitude": "-28.96836000",
      "longitude": "-51.97107000"
    },
    {
      "id": 10280,
      "name": "Antônio Prado",
      "latitude": "-28.87322000",
      "longitude": "-51.31744000"
    },
    {
      "id": 10331,
      "name": "Arambaré",
      "latitude": "-30.91331000",
      "longitude": "-51.55614000"
    },
    {
      "id": 10353,
      "name": "Araricá",
      "latitude": "-29.64987000",
      "longitude": "-50.93350000"
    },
    {
      "id": 10360,
      "name": "Aratiba",
      "latitude": "-27.37708000",
      "longitude": "-52.29009000"
    },
    {
      "id": 10412,
      "name": "Arroio do Meio",
      "latitude": "-29.40111000",
      "longitude": "-51.94500000"
    },
    {
      "id": 10413,
      "name": "Arroio do Padre",
      "latitude": "-31.43927000",
      "longitude": "-52.39642000"
    },
    {
      "id": 10414,
      "name": "Arroio do Sal",
      "latitude": "-29.52930000",
      "longitude": "-49.89148000"
    },
    {
      "id": 10415,
      "name": "Arroio do Tigre",
      "latitude": "-29.26209000",
      "longitude": "-53.06060000"
    },
    {
      "id": 10416,
      "name": "Arroio dos Ratos",
      "latitude": "-30.07722000",
      "longitude": "-51.72917000"
    },
    {
      "id": 10410,
      "name": "Arroio Grande",
      "latitude": "-32.17945000",
      "longitude": "-52.86652000"
    },
    {
      "id": 10421,
      "name": "Arvorezinha",
      "latitude": "-28.86971000",
      "longitude": "-52.19631000"
    },
    {
      "id": 10444,
      "name": "Augusto Pestana",
      "latitude": "-28.54034000",
      "longitude": "-53.97927000"
    },
    {
      "id": 15680,
      "name": "Áurea",
      "latitude": "-27.69538000",
      "longitude": "-52.06560000"
    },
    {
      "id": 10474,
      "name": "Bagé",
      "latitude": "-31.33139000",
      "longitude": "-54.10694000"
    },
    {
      "id": 10488,
      "name": "Balneário Pinhal",
      "latitude": "-30.21275000",
      "longitude": "-50.29309000"
    },
    {
      "id": 10570,
      "name": "Barão",
      "latitude": "-29.39636000",
      "longitude": "-51.54620000"
    },
    {
      "id": 10573,
      "name": "Barão de Cotegipe",
      "latitude": "-27.55108000",
      "longitude": "-52.44751000"
    },
    {
      "id": 10577,
      "name": "Barão do Triunfo",
      "latitude": "-30.39257000",
      "longitude": "-51.79493000"
    },
    {
      "id": 10536,
      "name": "Barra do Guarita",
      "latitude": "-27.21739000",
      "longitude": "-53.76461000"
    },
    {
      "id": 10541,
      "name": "Barra do Quaraí",
      "latitude": "-30.17445000",
      "longitude": "-57.31007000"
    },
    {
      "id": 10542,
      "name": "Barra do Ribeiro",
      "latitude": "-30.34435000",
      "longitude": "-51.36125000"
    },
    {
      "id": 10543,
      "name": "Barra do Rio Azul",
      "latitude": "-27.39848000",
      "longitude": "-52.40887000"
    },
    {
      "id": 10518,
      "name": "Barra Funda",
      "latitude": "-27.91562000",
      "longitude": "-53.03286000"
    },
    {
      "id": 10548,
      "name": "Barracão",
      "latitude": "-27.73726000",
      "longitude": "-51.44229000"
    },
    {
      "id": 10567,
      "name": "Barros Cassal",
      "latitude": "-29.13534000",
      "longitude": "-52.57508000"
    },
    {
      "id": 10627,
      "name": "Benjamin Constant do Sul",
      "latitude": "-27.48726000",
      "longitude": "-52.65470000"
    },
    {
      "id": 10629,
      "name": "Bento Gonçalves",
      "latitude": "-29.09958000",
      "longitude": "-51.54344000"
    },
    {
      "id": 10669,
      "name": "Boa Vista das Missões",
      "latitude": "-27.69239000",
      "longitude": "-53.35253000"
    },
    {
      "id": 10670,
      "name": "Boa Vista do Buricá",
      "latitude": "-27.68021000",
      "longitude": "-54.10928000"
    },
    {
      "id": 10671,
      "name": "Boa Vista do Cadeado",
      "latitude": "-28.62211000",
      "longitude": "-53.81616000"
    },
    {
      "id": 10673,
      "name": "Boa Vista do Incra",
      "latitude": "-28.84193000",
      "longitude": "-53.45649000"
    },
    {
      "id": 10675,
      "name": "Boa Vista do Sul",
      "latitude": "-29.34197000",
      "longitude": "-51.68079000"
    },
    {
      "id": 10701,
      "name": "Bom Jesus",
      "latitude": "-28.59981000",
      "longitude": "-50.46197000"
    },
    {
      "id": 10719,
      "name": "Bom Princípio",
      "latitude": "-29.46171000",
      "longitude": "-51.36405000"
    },
    {
      "id": 10721,
      "name": "Bom Progresso",
      "latitude": "-27.54223000",
      "longitude": "-53.82889000"
    },
    {
      "id": 10724,
      "name": "Bom Retiro do Sul",
      "latitude": "-29.63558000",
      "longitude": "-51.91097000"
    },
    {
      "id": 10744,
      "name": "Boqueirão do Leão",
      "latitude": "-29.31252000",
      "longitude": "-52.39841000"
    },
    {
      "id": 10756,
      "name": "Bossoroca",
      "latitude": "-28.67113000",
      "longitude": "-54.96188000"
    },
    {
      "id": 10762,
      "name": "Bozano",
      "latitude": "-28.36580000",
      "longitude": "-53.76893000"
    },
    {
      "id": 10763,
      "name": "Braga",
      "latitude": "-27.57218000",
      "longitude": "-53.76214000"
    },
    {
      "id": 10804,
      "name": "Brochier",
      "latitude": "-29.55754000",
      "longitude": "-51.59193000"
    },
    {
      "id": 10838,
      "name": "Butiá",
      "latitude": "-30.11972000",
      "longitude": "-51.96222000"
    },
    {
      "id": 11223,
      "name": "Caçapava do Sul",
      "latitude": "-30.61002000",
      "longitude": "-53.47227000"
    },
    {
      "id": 10860,
      "name": "Cacequi",
      "latitude": "-29.88361000",
      "longitude": "-54.82500000"
    },
    {
      "id": 10873,
      "name": "Cachoeira do Sul",
      "latitude": "-30.20808000",
      "longitude": "-52.97067000"
    },
    {
      "id": 10877,
      "name": "Cachoeirinha",
      "latitude": "-29.95111000",
      "longitude": "-51.09389000"
    },
    {
      "id": 10884,
      "name": "Cacique Doble",
      "latitude": "-27.81730000",
      "longitude": "-51.68271000"
    },
    {
      "id": 10901,
      "name": "Caibaté",
      "latitude": "-28.30429000",
      "longitude": "-54.65585000"
    },
    {
      "id": 10908,
      "name": "Caiçara",
      "latitude": "-27.24828000",
      "longitude": "-53.45824000"
    },
    {
      "id": 10940,
      "name": "Camaquã",
      "latitude": "-30.91965000",
      "longitude": "-51.85302000"
    },
    {
      "id": 10942,
      "name": "Camargo",
      "latitude": "-28.61437000",
      "longitude": "-52.21986000"
    },
    {
      "id": 10945,
      "name": "Cambará do Sul",
      "latitude": "-29.06727000",
      "longitude": "-50.11848000"
    },
    {
      "id": 10959,
      "name": "Campestre da Serra",
      "latitude": "-28.70645000",
      "longitude": "-51.11921000"
    },
    {
      "id": 10966,
      "name": "Campina das Missões",
      "latitude": "-27.98729000",
      "longitude": "-54.83020000"
    },
    {
      "id": 10972,
      "name": "Campinas do Sul",
      "latitude": "-27.70629000",
      "longitude": "-52.63937000"
    },
    {
      "id": 10984,
      "name": "Campo Bom",
      "latitude": "-29.66716000",
      "longitude": "-51.05054000"
    },
    {
      "id": 10999,
      "name": "Campo Novo",
      "latitude": "-27.67313000",
      "longitude": "-53.81745000"
    },
    {
      "id": 11010,
      "name": "Campos Borges",
      "latitude": "-28.89387000",
      "longitude": "-53.02543000"
    },
    {
      "id": 11036,
      "name": "Candelária",
      "latitude": "-29.71623000",
      "longitude": "-52.80968000"
    },
    {
      "id": 11545,
      "name": "Cândido Godói",
      "latitude": "-27.89509000",
      "longitude": "-54.74128000"
    },
    {
      "id": 11038,
      "name": "Candiota",
      "latitude": "-31.49089000",
      "longitude": "-53.70274000"
    },
    {
      "id": 11040,
      "name": "Canela",
      "latitude": "-29.34715000",
      "longitude": "-50.77536000"
    },
    {
      "id": 11043,
      "name": "Canguçu",
      "latitude": "-31.39500000",
      "longitude": "-52.67556000"
    },
    {
      "id": 11049,
      "name": "Canoas",
      "latitude": "-29.91778000",
      "longitude": "-51.18361000"
    },
    {
      "id": 11058,
      "name": "Canudos do Vale",
      "latitude": "-29.32055000",
      "longitude": "-52.22476000"
    },
    {
      "id": 11097,
      "name": "Capão Bonito do Sul",
      "latitude": "-28.17432000",
      "longitude": "-51.42298000"
    },
    {
      "id": 11098,
      "name": "Capão da Canoa",
      "latitude": "-29.66118000",
      "longitude": "-50.01422000"
    },
    {
      "id": 11099,
      "name": "Capão do Cipó",
      "latitude": "-28.94987000",
      "longitude": "-54.60368000"
    },
    {
      "id": 11100,
      "name": "Capão do Leão",
      "latitude": "-31.84324000",
      "longitude": "-52.55323000"
    },
    {
      "id": 11068,
      "name": "Capela de Santana",
      "latitude": "-29.71236000",
      "longitude": "-51.38078000"
    },
    {
      "id": 11080,
      "name": "Capitão",
      "latitude": "-29.28020000",
      "longitude": "-51.98317000"
    },
    {
      "id": 11090,
      "name": "Capivari do Sul",
      "latitude": "-30.17289000",
      "longitude": "-50.48702000"
    },
    {
      "id": 11114,
      "name": "Caraá",
      "latitude": "-29.77397000",
      "longitude": "-50.35369000"
    },
    {
      "id": 11113,
      "name": "Carazinho",
      "latitude": "-28.28389000",
      "longitude": "-52.78639000"
    },
    {
      "id": 11138,
      "name": "Carlos Barbosa",
      "latitude": "-29.29750000",
      "longitude": "-51.50361000"
    },
    {
      "id": 11140,
      "name": "Carlos Gomes",
      "latitude": "-27.71183000",
      "longitude": "-51.90645000"
    },
    {
      "id": 11174,
      "name": "Casca",
      "latitude": "-28.57590000",
      "longitude": "-51.91980000"
    },
    {
      "id": 11179,
      "name": "Caseiros",
      "latitude": "-28.23222000",
      "longitude": "-51.78157000"
    },
    {
      "id": 11213,
      "name": "Catuípe",
      "latitude": "-28.19806000",
      "longitude": "-54.05868000"
    },
    {
      "id": 11219,
      "name": "Caxias do Sul",
      "latitude": "-29.16806000",
      "longitude": "-51.17944000"
    },
    {
      "id": 11236,
      "name": "Centenário",
      "latitude": "-27.78654000",
      "longitude": "-52.00905000"
    },
    {
      "id": 11248,
      "name": "Cerrito",
      "latitude": "-31.73952000",
      "longitude": "-52.78378000"
    },
    {
      "id": 11250,
      "name": "Cerro Branco",
      "latitude": "-29.63374000",
      "longitude": "-52.98725000"
    },
    {
      "id": 11252,
      "name": "Cerro Grande",
      "latitude": "-27.62261000",
      "longitude": "-53.16028000"
    },
    {
      "id": 11253,
      "name": "Cerro Grande do Sul",
      "latitude": "-30.58623000",
      "longitude": "-51.74239000"
    },
    {
      "id": 11254,
      "name": "Cerro Largo",
      "latitude": "-28.13490000",
      "longitude": "-54.73667000"
    },
    {
      "id": 11259,
      "name": "Chapada",
      "latitude": "-28.10434000",
      "longitude": "-53.08861000"
    },
    {
      "id": 11271,
      "name": "Charqueadas",
      "latitude": "-29.95472000",
      "longitude": "-51.62528000"
    },
    {
      "id": 11272,
      "name": "Charrua",
      "latitude": "-27.94543000",
      "longitude": "-51.99053000"
    },
    {
      "id": 11277,
      "name": "Chiapetta",
      "latitude": "-27.97630000",
      "longitude": "-53.92051000"
    },
    {
      "id": 11284,
      "name": "Chuí",
      "latitude": "-33.69111000",
      "longitude": "-53.45667000"
    },
    {
      "id": 11283,
      "name": "Chuvisca",
      "latitude": "-30.77649000",
      "longitude": "-52.00221000"
    },
    {
      "id": 11293,
      "name": "Cidreira",
      "latitude": "-30.09103000",
      "longitude": "-50.26938000"
    },
    {
      "id": 11296,
      "name": "Ciríaco",
      "latitude": "-28.37066000",
      "longitude": "-51.91242000"
    },
    {
      "id": 11323,
      "name": "Colinas",
      "latitude": "-29.39282000",
      "longitude": "-51.86831000"
    },
    {
      "id": 11330,
      "name": "Colorado",
      "latitude": "-28.48320000",
      "longitude": "-52.99088000"
    },
    {
      "id": 11374,
      "name": "Condor",
      "latitude": "-28.19261000",
      "longitude": "-53.49261000"
    },
    {
      "id": 11388,
      "name": "Constantina",
      "latitude": "-27.70625000",
      "longitude": "-53.00221000"
    },
    {
      "id": 11393,
      "name": "Coqueiro Baixo",
      "latitude": "-29.17479000",
      "longitude": "-52.10209000"
    },
    {
      "id": 11395,
      "name": "Coqueiros do Sul",
      "latitude": "-28.13683000",
      "longitude": "-52.76136000"
    },
    {
      "id": 11415,
      "name": "Coronel Barros",
      "latitude": "-28.39445000",
      "longitude": "-54.06367000"
    },
    {
      "id": 11416,
      "name": "Coronel Bicaco",
      "latitude": "-27.79949000",
      "longitude": "-53.65310000"
    },
    {
      "id": 11428,
      "name": "Coronel Pilar",
      "latitude": "-29.25977000",
      "longitude": "-51.71821000"
    },
    {
      "id": 11453,
      "name": "Cotiporã",
      "latitude": "-29.00719000",
      "longitude": "-51.69528000"
    },
    {
      "id": 11457,
      "name": "Coxilha",
      "latitude": "-28.10327000",
      "longitude": "-52.36576000"
    },
    {
      "id": 11466,
      "name": "Crissiumal",
      "latitude": "-27.48087000",
      "longitude": "-54.14173000"
    },
    {
      "id": 11469,
      "name": "Cristal",
      "latitude": "-31.02454000",
      "longitude": "-52.02929000"
    },
    {
      "id": 11470,
      "name": "Cristal do Sul",
      "latitude": "-27.42515000",
      "longitude": "-53.24362000"
    },
    {
      "id": 11489,
      "name": "Cruz Alta",
      "latitude": "-28.64397000",
      "longitude": "-53.60633000"
    },
    {
      "id": 11493,
      "name": "Cruzaltense",
      "latitude": "-27.64105000",
      "longitude": "-52.63264000"
    },
    {
      "id": 11500,
      "name": "Cruzeiro do Sul",
      "latitude": "-29.56709000",
      "longitude": "-52.03042000"
    },
    {
      "id": 11564,
      "name": "David Canabarro",
      "latitude": "-28.41776000",
      "longitude": "-51.81680000"
    },
    {
      "id": 11575,
      "name": "Derrubadas",
      "latitude": "-27.25025000",
      "longitude": "-53.88415000"
    },
    {
      "id": 11582,
      "name": "Dezesseis de Novembro",
      "latitude": "-28.19125000",
      "longitude": "-55.07548000"
    },
    {
      "id": 11592,
      "name": "Dilermando de Aguiar",
      "latitude": "-29.80603000",
      "longitude": "-54.15398000"
    },
    {
      "id": 11614,
      "name": "Dois Irmãos",
      "latitude": "-29.61158000",
      "longitude": "-51.09333000"
    },
    {
      "id": 11615,
      "name": "Dois Irmãos das Missões",
      "latitude": "-27.68117000",
      "longitude": "-53.51477000"
    },
    {
      "id": 11618,
      "name": "Dois Lajeados",
      "latitude": "-28.97092000",
      "longitude": "-51.84970000"
    },
    {
      "id": 11628,
      "name": "Dom Feliciano",
      "latitude": "-30.61390000",
      "longitude": "-52.19315000"
    },
    {
      "id": 11632,
      "name": "Dom Pedrito",
      "latitude": "-30.98278000",
      "longitude": "-54.67306000"
    },
    {
      "id": 11634,
      "name": "Dom Pedro de Alcântara",
      "latitude": "-29.35681000",
      "longitude": "-49.87288000"
    },
    {
      "id": 11641,
      "name": "Dona Francisca",
      "latitude": "-29.58683000",
      "longitude": "-53.33964000"
    },
    {
      "id": 11656,
      "name": "Doutor Maurício Cardoso",
      "latitude": "-27.49540000",
      "longitude": "-54.36400000"
    },
    {
      "id": 11658,
      "name": "Doutor Ricardo",
      "latitude": "-29.10117000",
      "longitude": "-51.97440000"
    },
    {
      "id": 11680,
      "name": "Eldorado do Sul",
      "latitude": "-30.08896000",
      "longitude": "-51.53400000"
    },
    {
      "id": 11694,
      "name": "Encantado",
      "latitude": "-29.23611000",
      "longitude": "-51.86972000"
    },
    {
      "id": 11697,
      "name": "Encruzilhada do Sul",
      "latitude": "-30.60368000",
      "longitude": "-52.68280000"
    },
    {
      "id": 11703,
      "name": "Engenho Velho",
      "latitude": "-27.67698000",
      "longitude": "-52.91040000"
    },
    {
      "id": 11709,
      "name": "Entre Rios do Sul",
      "latitude": "-27.50821000",
      "longitude": "-52.72855000"
    },
    {
      "id": 11710,
      "name": "Entre-Ijuís",
      "latitude": "-28.46066000",
      "longitude": "-54.30321000"
    },
    {
      "id": 11715,
      "name": "Erebango",
      "latitude": "-27.82558000",
      "longitude": "-52.31909000"
    },
    {
      "id": 11716,
      "name": "Erechim",
      "latitude": "-27.63461000",
      "longitude": "-52.27540000"
    },
    {
      "id": 11719,
      "name": "Ernestina",
      "latitude": "-28.42323000",
      "longitude": "-52.57365000"
    },
    {
      "id": 11720,
      "name": "Erval Grande",
      "latitude": "-27.36138000",
      "longitude": "-52.57486000"
    },
    {
      "id": 11721,
      "name": "Erval Seco",
      "latitude": "-27.49433000",
      "longitude": "-53.52792000"
    },
    {
      "id": 11725,
      "name": "Esmeralda",
      "latitude": "-27.98347000",
      "longitude": "-51.19413000"
    },
    {
      "id": 11733,
      "name": "Esperança do Sul",
      "latitude": "-27.32100000",
      "longitude": "-54.01108000"
    },
    {
      "id": 11738,
      "name": "Espumoso",
      "latitude": "-28.72472000",
      "longitude": "-52.84972000"
    },
    {
      "id": 11743,
      "name": "Estação",
      "latitude": "-27.93562000",
      "longitude": "-52.29516000"
    },
    {
      "id": 11758,
      "name": "Estância Velha",
      "latitude": "-29.64833000",
      "longitude": "-51.17389000"
    },
    {
      "id": 11744,
      "name": "Esteio",
      "latitude": "-29.86139000",
      "longitude": "-51.17917000"
    },
    {
      "id": 11748,
      "name": "Estrela",
      "latitude": "-28.06111000",
      "longitude": "-50.93833000"
    },
    {
      "id": 11750,
      "name": "Estrela Velha",
      "latitude": "-29.22360000",
      "longitude": "-53.17076000"
    },
    {
      "id": 11762,
      "name": "Eugênio de Castro",
      "latitude": "-28.57179000",
      "longitude": "-54.26582000"
    },
    {
      "id": 11771,
      "name": "Fagundes Varela",
      "latitude": "-28.88133000",
      "longitude": "-51.72861000"
    },
    {
      "id": 11778,
      "name": "Farroupilha",
      "latitude": "-29.22500000",
      "longitude": "-51.34778000"
    },
    {
      "id": 11782,
      "name": "Faxinal do Soturno",
      "latitude": "-29.57197000",
      "longitude": "-53.47332000"
    },
    {
      "id": 11784,
      "name": "Faxinalzinho",
      "latitude": "-27.37178000",
      "longitude": "-52.66899000"
    },
    {
      "id": 11787,
      "name": "Fazenda Vilanova",
      "latitude": "-29.59817000",
      "longitude": "-51.84244000"
    },
    {
      "id": 11798,
      "name": "Feliz",
      "latitude": "-29.45459000",
      "longitude": "-51.27775000"
    },
    {
      "id": 11831,
      "name": "Flores da Cunha",
      "latitude": "-29.02889000",
      "longitude": "-51.18167000"
    },
    {
      "id": 11842,
      "name": "Floriano Peixoto",
      "latitude": "-27.85241000",
      "longitude": "-52.03361000"
    },
    {
      "id": 11849,
      "name": "Fontoura Xavier",
      "latitude": "-29.01054000",
      "longitude": "-52.36771000"
    },
    {
      "id": 11851,
      "name": "Formigueiro",
      "latitude": "-29.96944000",
      "longitude": "-53.46743000"
    },
    {
      "id": 11860,
      "name": "Forquetinha",
      "latitude": "-29.39695000",
      "longitude": "-52.11762000"
    },
    {
      "id": 11867,
      "name": "Fortaleza dos Valos",
      "latitude": "-28.91268000",
      "longitude": "-53.33891000"
    },
    {
      "id": 11889,
      "name": "Frederico Westphalen",
      "latitude": "-27.35917000",
      "longitude": "-53.39444000"
    },
    {
      "id": 11921,
      "name": "Garibaldi",
      "latitude": "-29.25611000",
      "longitude": "-51.53361000"
    },
    {
      "id": 11924,
      "name": "Garruchos",
      "latitude": "-28.25602000",
      "longitude": "-55.51556000"
    },
    {
      "id": 11929,
      "name": "Gaurama",
      "latitude": "-27.61693000",
      "longitude": "-52.10405000"
    },
    {
      "id": 11936,
      "name": "General Câmara",
      "latitude": "-29.83922000",
      "longitude": "-51.94718000"
    },
    {
      "id": 11940,
      "name": "Gentil",
      "latitude": "-28.38797000",
      "longitude": "-52.04926000"
    },
    {
      "id": 11943,
      "name": "Getúlio Vargas",
      "latitude": "-27.87411000",
      "longitude": "-52.16526000"
    },
    {
      "id": 11946,
      "name": "Giruá",
      "latitude": "-28.01046000",
      "longitude": "-54.30456000"
    },
    {
      "id": 11949,
      "name": "Glorinha",
      "latitude": "-29.85685000",
      "longitude": "-50.75086000"
    },
    {
      "id": 11993,
      "name": "Gramado",
      "latitude": "-29.36252000",
      "longitude": "-50.90318000"
    },
    {
      "id": 11995,
      "name": "Gramado dos Loureiros",
      "latitude": "-27.45441000",
      "longitude": "-52.91705000"
    },
    {
      "id": 11994,
      "name": "Gramado Xavier",
      "latitude": "-29.28655000",
      "longitude": "-52.61202000"
    },
    {
      "id": 12001,
      "name": "Gravataí",
      "latitude": "-29.94218000",
      "longitude": "-50.99278000"
    },
    {
      "id": 12010,
      "name": "Guabiju",
      "latitude": "-28.58817000",
      "longitude": "-51.64765000"
    },
    {
      "id": 12076,
      "name": "Guaíba",
      "latitude": "-30.11389000",
      "longitude": "-51.32500000"
    },
    {
      "id": 12031,
      "name": "Guaporé",
      "latitude": "-28.84191000",
      "longitude": "-51.91880000"
    },
    {
      "id": 12045,
      "name": "Guarani das Missões",
      "latitude": "-28.15071000",
      "longitude": "-54.60026000"
    },
    {
      "id": 12092,
      "name": "Harmonia",
      "latitude": "-29.54904000",
      "longitude": "-51.42357000"
    },
    {
      "id": 12097,
      "name": "Herval",
      "latitude": "-32.02361000",
      "longitude": "-53.39556000"
    },
    {
      "id": 12099,
      "name": "Herveiras",
      "latitude": "-29.43864000",
      "longitude": "-52.67366000"
    },
    {
      "id": 12106,
      "name": "Horizontina",
      "latitude": "-27.62583000",
      "longitude": "-54.30778000"
    },
    {
      "id": 12109,
      "name": "Hulha Negra",
      "latitude": "-31.57199000",
      "longitude": "-53.86271000"
    },
    {
      "id": 12111,
      "name": "Humaitá",
      "latitude": "-27.58561000",
      "longitude": "-53.99627000"
    },
    {
      "id": 12121,
      "name": "Ibarama",
      "latitude": "-29.40889000",
      "longitude": "-53.18252000"
    },
    {
      "id": 12132,
      "name": "Ibiaçá",
      "latitude": "-28.10474000",
      "longitude": "-51.80283000"
    },
    {
      "id": 12146,
      "name": "Ibiraiaras",
      "latitude": "-28.38729000",
      "longitude": "-51.62710000"
    },
    {
      "id": 12150,
      "name": "Ibirapuitã",
      "latitude": "-28.61696000",
      "longitude": "-52.47077000"
    },
    {
      "id": 12156,
      "name": "Ibirubá",
      "latitude": "-28.62750000",
      "longitude": "-53.08972000"
    },
    {
      "id": 12194,
      "name": "Igrejinha",
      "latitude": "-29.57444000",
      "longitude": "-50.79028000"
    },
    {
      "id": 12205,
      "name": "Ijuí",
      "latitude": "-28.38778000",
      "longitude": "-53.91472000"
    },
    {
      "id": 12216,
      "name": "Ilópolis",
      "latitude": "-28.91690000",
      "longitude": "-52.14813000"
    },
    {
      "id": 12223,
      "name": "Imbé",
      "latitude": "-29.92719000",
      "longitude": "-50.12826000"
    },
    {
      "id": 12225,
      "name": "Imigrante",
      "latitude": "-29.34023000",
      "longitude": "-51.75667000"
    },
    {
      "id": 12235,
      "name": "Independência",
      "latitude": "-27.89333000",
      "longitude": "-54.19784000"
    },
    {
      "id": 12246,
      "name": "Inhacorá",
      "latitude": "-27.91435000",
      "longitude": "-54.03786000"
    },
    {
      "id": 12299,
      "name": "Ipê",
      "latitude": "-28.71616000",
      "longitude": "-51.27787000"
    },
    {
      "id": 12279,
      "name": "Ipiranga do Sul",
      "latitude": "-27.94208000",
      "longitude": "-52.43068000"
    },
    {
      "id": 12315,
      "name": "Iraí",
      "latitude": "-27.27078000",
      "longitude": "-53.23696000"
    },
    {
      "id": 12324,
      "name": "Itaara",
      "latitude": "-29.56305000",
      "longitude": "-53.74584000"
    },
    {
      "id": 12345,
      "name": "Itacurubi",
      "latitude": "-28.78540000",
      "longitude": "-55.26568000"
    },
    {
      "id": 12436,
      "name": "Itapuca",
      "latitude": "-28.77178000",
      "longitude": "-52.20012000"
    },
    {
      "id": 12444,
      "name": "Itaqui",
      "latitude": "-29.12528000",
      "longitude": "-56.55306000"
    },
    {
      "id": 12453,
      "name": "Itati",
      "latitude": "-29.42840000",
      "longitude": "-50.17775000"
    },
    {
      "id": 12457,
      "name": "Itatiba do Sul",
      "latitude": "-27.36303000",
      "longitude": "-52.49074000"
    },
    {
      "id": 12504,
      "name": "Ivorá",
      "latitude": "-29.50743000",
      "longitude": "-53.56819000"
    },
    {
      "id": 12505,
      "name": "Ivoti",
      "latitude": "-29.59111000",
      "longitude": "-51.16056000"
    },
    {
      "id": 12514,
      "name": "Jaboticaba",
      "latitude": "-27.60969000",
      "longitude": "-53.27016000"
    },
    {
      "id": 12529,
      "name": "Jacuizinho",
      "latitude": "-29.03095000",
      "longitude": "-53.06796000"
    },
    {
      "id": 12532,
      "name": "Jacutinga",
      "latitude": "-27.77469000",
      "longitude": "-52.52224000"
    },
    {
      "id": 12549,
      "name": "Jaguarão",
      "latitude": "-32.56611000",
      "longitude": "-53.37583000"
    },
    {
      "id": 12541,
      "name": "Jaguari",
      "latitude": "-29.45245000",
      "longitude": "-54.64626000"
    },
    {
      "id": 12578,
      "name": "Jaquirana",
      "latitude": "-28.93470000",
      "longitude": "-50.36430000"
    },
    {
      "id": 12594,
      "name": "Jari",
      "latitude": "-29.28796000",
      "longitude": "-54.29784000"
    },
    {
      "id": 12716,
      "name": "Jóia",
      "latitude": "-28.72932000",
      "longitude": "-54.12253000"
    },
    {
      "id": 12719,
      "name": "Júlio de Castilhos",
      "latitude": "-29.26449000",
      "longitude": "-53.62459000"
    },
    {
      "id": 12735,
      "name": "Lagoa Bonita do Sul",
      "latitude": "-29.49396000",
      "longitude": "-53.03470000"
    },
    {
      "id": 12767,
      "name": "Lagoa dos Três Cantos",
      "latitude": "-28.56607000",
      "longitude": "-52.84650000"
    },
    {
      "id": 12747,
      "name": "Lagoa Vermelha",
      "latitude": "-28.21995000",
      "longitude": "-51.47225000"
    },
    {
      "id": 12770,
      "name": "Lagoão",
      "latitude": "-29.25902000",
      "longitude": "-52.76687000"
    },
    {
      "id": 12775,
      "name": "Lajeado",
      "latitude": "-29.46694000",
      "longitude": "-51.96139000"
    },
    {
      "id": 12779,
      "name": "Lajeado do Bugre",
      "latitude": "-27.70327000",
      "longitude": "-53.20742000"
    },
    {
      "id": 12810,
      "name": "Lavras do Sul",
      "latitude": "-30.84980000",
      "longitude": "-54.02830000"
    },
    {
      "id": 12823,
      "name": "Liberato Salzano",
      "latitude": "-27.53845000",
      "longitude": "-53.07401000"
    },
    {
      "id": 12836,
      "name": "Lindolfo Collor",
      "latitude": "-29.57482000",
      "longitude": "-51.22786000"
    },
    {
      "id": 12839,
      "name": "Linha Nova",
      "latitude": "-29.45535000",
      "longitude": "-51.21876000"
    },
    {
      "id": 13089,
      "name": "Maçambará",
      "latitude": "-29.05822000",
      "longitude": "-55.61102000"
    },
    {
      "id": 12898,
      "name": "Machadinho",
      "latitude": "-27.59183000",
      "longitude": "-51.68758000"
    },
    {
      "id": 12935,
      "name": "Mampituba",
      "latitude": "-29.26145000",
      "longitude": "-50.01070000"
    },
    {
      "id": 12955,
      "name": "Manoel Viana",
      "latitude": "-29.40696000",
      "longitude": "-55.56870000"
    },
    {
      "id": 12960,
      "name": "Maquiné",
      "latitude": "-29.57608000",
      "longitude": "-50.25993000"
    },
    {
      "id": 12983,
      "name": "Maratá",
      "latitude": "-29.54921000",
      "longitude": "-51.55693000"
    },
    {
      "id": 12984,
      "name": "Marau",
      "latitude": "-28.44217000",
      "longitude": "-52.27411000"
    },
    {
      "id": 12991,
      "name": "Marcelino Ramos",
      "latitude": "-27.47851000",
      "longitude": "-51.95065000"
    },
    {
      "id": 13008,
      "name": "Mariana Pimentel",
      "latitude": "-30.30220000",
      "longitude": "-51.58133000"
    },
    {
      "id": 13009,
      "name": "Mariano Moro",
      "latitude": "-27.35013000",
      "longitude": "-52.18363000"
    },
    {
      "id": 13029,
      "name": "Marques de Souza",
      "latitude": "-29.27327000",
      "longitude": "-52.15720000"
    },
    {
      "id": 13045,
      "name": "Mata",
      "latitude": "-29.54895000",
      "longitude": "-54.44545000"
    },
    {
      "id": 13064,
      "name": "Mato Castelhano",
      "latitude": "-28.27248000",
      "longitude": "-52.17628000"
    },
    {
      "id": 13066,
      "name": "Mato Leitão",
      "latitude": "-29.51457000",
      "longitude": "-52.13856000"
    },
    {
      "id": 13067,
      "name": "Mato Queimado",
      "latitude": "-28.25680000",
      "longitude": "-54.67109000"
    },
    {
      "id": 13087,
      "name": "Maximiliano de Almeida",
      "latitude": "-27.58802000",
      "longitude": "-51.80358000"
    },
    {
      "id": 13123,
      "name": "Minas do Leão",
      "latitude": "-30.07189000",
      "longitude": "-52.11996000"
    },
    {
      "id": 13137,
      "name": "Miraguaí",
      "latitude": "-27.48658000",
      "longitude": "-53.75549000"
    },
    {
      "id": 13185,
      "name": "Montauri",
      "latitude": "-28.66498000",
      "longitude": "-52.05388000"
    },
    {
      "id": 13193,
      "name": "Monte Alegre dos Campos",
      "latitude": "-28.70177000",
      "longitude": "-50.80405000"
    },
    {
      "id": 13199,
      "name": "Monte Belo do Sul",
      "latitude": "-29.13180000",
      "longitude": "-51.64287000"
    },
    {
      "id": 13218,
      "name": "Montenegro",
      "latitude": "-29.68861000",
      "longitude": "-51.46111000"
    },
    {
      "id": 13233,
      "name": "Mormaço",
      "latitude": "-28.69004000",
      "longitude": "-52.66928000"
    },
    {
      "id": 13238,
      "name": "Morrinhos do Sul",
      "latitude": "-29.34362000",
      "longitude": "-49.96435000"
    },
    {
      "id": 13243,
      "name": "Morro Redondo",
      "latitude": "-31.63833000",
      "longitude": "-52.63569000"
    },
    {
      "id": 13244,
      "name": "Morro Reuter",
      "latitude": "-29.51567000",
      "longitude": "-51.01861000"
    },
    {
      "id": 13256,
      "name": "Mostardas",
      "latitude": "-30.92226000",
      "longitude": "-50.85421000"
    },
    {
      "id": 13289,
      "name": "Muçum",
      "latitude": "-29.14017000",
      "longitude": "-51.82330000"
    },
    {
      "id": 13264,
      "name": "Muitos Capões",
      "latitude": "-28.43447000",
      "longitude": "-51.24691000"
    },
    {
      "id": 13265,
      "name": "Muliterno",
      "latitude": "-28.31235000",
      "longitude": "-51.78652000"
    },
    {
      "id": 13485,
      "name": "Não Me Toque",
      "latitude": "-28.45917000",
      "longitude": "-52.82083000"
    },
    {
      "id": 13486,
      "name": "Não-Me-Toque",
      "latitude": "-28.47423000",
      "longitude": "-52.80396000"
    },
    {
      "id": 13323,
      "name": "Nicolau Vergueiro",
      "latitude": "-28.52442000",
      "longitude": "-52.44444000"
    },
    {
      "id": 13333,
      "name": "Nonoai",
      "latitude": "-27.36903000",
      "longitude": "-52.87590000"
    },
    {
      "id": 13347,
      "name": "Nova Alvorada",
      "latitude": "-28.70497000",
      "longitude": "-52.16616000"
    },
    {
      "id": 13352,
      "name": "Nova Araçá",
      "latitude": "-28.64411000",
      "longitude": "-51.73489000"
    },
    {
      "id": 13356,
      "name": "Nova Bassano",
      "latitude": "-28.70293000",
      "longitude": "-51.80542000"
    },
    {
      "id": 13358,
      "name": "Nova Boa Vista",
      "latitude": "-28.00887000",
      "longitude": "-52.98206000"
    },
    {
      "id": 13361,
      "name": "Nova Bréscia",
      "latitude": "-29.20206000",
      "longitude": "-52.04822000"
    },
    {
      "id": 13366,
      "name": "Nova Candelária",
      "latitude": "-27.59344000",
      "longitude": "-54.12172000"
    },
    {
      "id": 13377,
      "name": "Nova Esperança do Sul",
      "latitude": "-29.39225000",
      "longitude": "-54.83460000"
    },
    {
      "id": 13387,
      "name": "Nova Hartz",
      "latitude": "-29.59640000",
      "longitude": "-50.90836000"
    },
    {
      "id": 13423,
      "name": "Nova Pádua",
      "latitude": "-29.01222000",
      "longitude": "-51.31451000"
    },
    {
      "id": 13416,
      "name": "Nova Palma",
      "latitude": "-29.40710000",
      "longitude": "-53.43240000"
    },
    {
      "id": 13418,
      "name": "Nova Petrópolis",
      "latitude": "-29.37639000",
      "longitude": "-51.11444000"
    },
    {
      "id": 13421,
      "name": "Nova Prata",
      "latitude": "-28.78389000",
      "longitude": "-51.61000000"
    },
    {
      "id": 13424,
      "name": "Nova Ramada",
      "latitude": "-28.09297000",
      "longitude": "-53.69502000"
    },
    {
      "id": 13428,
      "name": "Nova Roma do Sul",
      "latitude": "-28.99091000",
      "longitude": "-51.41443000"
    },
    {
      "id": 13434,
      "name": "Nova Santa Rita",
      "latitude": "-29.83265000",
      "longitude": "-51.27431000"
    },
    {
      "id": 13454,
      "name": "Novo Barreiro",
      "latitude": "-27.89154000",
      "longitude": "-53.11220000"
    },
    {
      "id": 13456,
      "name": "Novo Cabrais",
      "latitude": "-29.76161000",
      "longitude": "-52.98402000"
    },
    {
      "id": 13459,
      "name": "Novo Hamburgo",
      "latitude": "-29.67833000",
      "longitude": "-51.13056000"
    },
    {
      "id": 13469,
      "name": "Novo Machado",
      "latitude": "-27.55482000",
      "longitude": "-54.53613000"
    },
    {
      "id": 13480,
      "name": "Novo Tiradentes",
      "latitude": "-27.55948000",
      "longitude": "-53.15567000"
    },
    {
      "id": 13482,
      "name": "Novo Xingu",
      "latitude": "-27.74556000",
      "longitude": "-53.04043000"
    },
    {
      "id": 13530,
      "name": "Osório",
      "latitude": "-29.89454000",
      "longitude": "-50.23467000"
    },
    {
      "id": 13568,
      "name": "Paim Filho",
      "latitude": "-27.72984000",
      "longitude": "-51.78102000"
    },
    {
      "id": 13585,
      "name": "Palmares do Sul",
      "latitude": "-30.25778000",
      "longitude": "-50.50972000"
    },
    {
      "id": 13592,
      "name": "Palmeira das Missões",
      "latitude": "-27.89944000",
      "longitude": "-53.31361000"
    },
    {
      "id": 13607,
      "name": "Palmitinho",
      "latitude": "-27.32268000",
      "longitude": "-53.59220000"
    },
    {
      "id": 13612,
      "name": "Panambi",
      "latitude": "-28.29250000",
      "longitude": "-53.50167000"
    },
    {
      "id": 13618,
      "name": "Pantano Grande",
      "latitude": "-30.25817000",
      "longitude": "-52.34168000"
    },
    {
      "id": 13657,
      "name": "Paraí",
      "latitude": "-28.59575000",
      "longitude": "-51.79731000"
    },
    {
      "id": 13663,
      "name": "Paraíso do Sul",
      "latitude": "-29.72404000",
      "longitude": "-53.11162000"
    },
    {
      "id": 13668,
      "name": "Pareci Novo",
      "latitude": "-29.61153000",
      "longitude": "-51.42691000"
    },
    {
      "id": 13683,
      "name": "Parobé",
      "latitude": "-29.62861000",
      "longitude": "-50.83472000"
    },
    {
      "id": 13686,
      "name": "Passa Sete",
      "latitude": "-29.43060000",
      "longitude": "-52.86514000"
    },
    {
      "id": 13699,
      "name": "Passo do Sobrado",
      "latitude": "-29.73133000",
      "longitude": "-52.23175000"
    },
    {
      "id": 13696,
      "name": "Passo Fundo",
      "latitude": "-28.26278000",
      "longitude": "-52.40667000"
    },
    {
      "id": 13732,
      "name": "Paulo Bento",
      "latitude": "-27.73673000",
      "longitude": "-52.39667000"
    },
    {
      "id": 13739,
      "name": "Paverama",
      "latitude": "-29.59556000",
      "longitude": "-51.72344000"
    },
    {
      "id": 13762,
      "name": "Pedras Altas",
      "latitude": "-31.83276000",
      "longitude": "-53.63272000"
    },
    {
      "id": 13780,
      "name": "Pedro Osório",
      "latitude": "-31.95760000",
      "longitude": "-52.89419000"
    },
    {
      "id": 13790,
      "name": "Pejuçara",
      "latitude": "-28.45442000",
      "longitude": "-53.61044000"
    },
    {
      "id": 13791,
      "name": "Pelotas",
      "latitude": "-31.76997000",
      "longitude": "-52.34101000"
    },
    {
      "id": 13828,
      "name": "Picada Café",
      "latitude": "-29.44757000",
      "longitude": "-51.11522000"
    },
    {
      "id": 13859,
      "name": "Pinhal",
      "latitude": "-27.52636000",
      "longitude": "-53.23425000"
    },
    {
      "id": 13861,
      "name": "Pinhal da Serra",
      "latitude": "-27.88164000",
      "longitude": "-51.22450000"
    },
    {
      "id": 13860,
      "name": "Pinhal Grande",
      "latitude": "-29.27075000",
      "longitude": "-53.34587000"
    },
    {
      "id": 13867,
      "name": "Pinheirinho do Vale",
      "latitude": "-27.22637000",
      "longitude": "-53.63352000"
    },
    {
      "id": 13869,
      "name": "Pinheiro Machado",
      "latitude": "-31.57833000",
      "longitude": "-53.38111000"
    },
    {
      "id": 13871,
      "name": "Pinheiros",
      "latitude": "-29.78333000",
      "longitude": "-52.73333000"
    },
    {
      "id": 13876,
      "name": "Pinto Bandeira",
      "latitude": "-29.09289000",
      "longitude": "-51.46180000"
    },
    {
      "id": 13903,
      "name": "Pirapó",
      "latitude": "-28.05287000",
      "longitude": "-55.23460000"
    },
    {
      "id": 13907,
      "name": "Piratini",
      "latitude": "-31.41655000",
      "longitude": "-53.11163000"
    },
    {
      "id": 13940,
      "name": "Planalto",
      "latitude": "-27.34391000",
      "longitude": "-53.08947000"
    },
    {
      "id": 14050,
      "name": "Poço das Antas",
      "latitude": "-29.45339000",
      "longitude": "-51.66969000"
    },
    {
      "id": 13979,
      "name": "Pontão",
      "latitude": "-28.04977000",
      "longitude": "-52.63740000"
    },
    {
      "id": 13971,
      "name": "Ponte Preta",
      "latitude": "-27.67688000",
      "longitude": "-52.51736000"
    },
    {
      "id": 14029,
      "name": "Portão",
      "latitude": "-29.70746000",
      "longitude": "-51.23572000"
    },
    {
      "id": 13994,
      "name": "Porto Alegre",
      "latitude": "-30.03283000",
      "longitude": "-51.23019000"
    },
    {
      "id": 14009,
      "name": "Porto Lucena",
      "latitude": "-27.84663000",
      "longitude": "-54.96059000"
    },
    {
      "id": 14010,
      "name": "Porto Mauá",
      "latitude": "-27.59808000",
      "longitude": "-54.65773000"
    },
    {
      "id": 14020,
      "name": "Porto Vera Cruz",
      "latitude": "-27.76244000",
      "longitude": "-54.90094000"
    },
    {
      "id": 14023,
      "name": "Porto Xavier",
      "latitude": "-27.93317000",
      "longitude": "-55.15422000"
    },
    {
      "id": 14040,
      "name": "Pouso Novo",
      "latitude": "-29.16777000",
      "longitude": "-52.22165000"
    },
    {
      "id": 14090,
      "name": "Presidente Lucena",
      "latitude": "-29.52778000",
      "longitude": "-51.19285000"
    },
    {
      "id": 14109,
      "name": "Progresso",
      "latitude": "-29.22873000",
      "longitude": "-52.30960000"
    },
    {
      "id": 14112,
      "name": "Protásio Alves",
      "latitude": "-28.74413000",
      "longitude": "-51.49620000"
    },
    {
      "id": 14117,
      "name": "Putinga",
      "latitude": "-29.04776000",
      "longitude": "-52.16503000"
    },
    {
      "id": 14126,
      "name": "Quaraí",
      "latitude": "-30.38750000",
      "longitude": "-56.45139000"
    },
    {
      "id": 14133,
      "name": "Quatro Irmãos",
      "latitude": "-27.81251000",
      "longitude": "-52.46069000"
    },
    {
      "id": 14147,
      "name": "Quevedos",
      "latitude": "-29.30670000",
      "longitude": "-54.07002000"
    },
    {
      "id": 14152,
      "name": "Quinze de Novembro",
      "latitude": "-28.74442000",
      "longitude": "-53.11648000"
    },
    {
      "id": 14182,
      "name": "Redentora",
      "latitude": "-27.56833000",
      "longitude": "-53.60924000"
    },
    {
      "id": 14192,
      "name": "Relvado",
      "latitude": "-29.12666000",
      "longitude": "-52.05393000"
    },
    {
      "id": 14206,
      "name": "Restinga Sêca",
      "latitude": "-29.82715000",
      "longitude": "-53.34008000"
    },
    {
      "id": 14319,
      "name": "Rio dos Índios",
      "latitude": "-27.25523000",
      "longitude": "-52.87641000"
    },
    {
      "id": 14276,
      "name": "Rio Grande",
      "latitude": "-32.07811000",
      "longitude": "-52.35014000"
    },
    {
      "id": 14288,
      "name": "Rio Pardo",
      "latitude": "-29.98972000",
      "longitude": "-52.37806000"
    },
    {
      "id": 14321,
      "name": "Riozinho",
      "latitude": "-29.59847000",
      "longitude": "-50.39225000"
    },
    {
      "id": 14325,
      "name": "Roca Sales",
      "latitude": "-29.22637000",
      "longitude": "-51.82440000"
    },
    {
      "id": 14329,
      "name": "Rodeio Bonito",
      "latitude": "-27.46968000",
      "longitude": "-53.17038000"
    },
    {
      "id": 14334,
      "name": "Rolador",
      "latitude": "-28.27096000",
      "longitude": "-54.85608000"
    },
    {
      "id": 14335,
      "name": "Rolante",
      "latitude": "-29.65056000",
      "longitude": "-50.57583000"
    },
    {
      "id": 14341,
      "name": "Ronda Alta",
      "latitude": "-27.82614000",
      "longitude": "-52.72873000"
    },
    {
      "id": 14342,
      "name": "Rondinha",
      "latitude": "-27.83287000",
      "longitude": "-52.91661000"
    },
    {
      "id": 14347,
      "name": "Roque Gonzales",
      "latitude": "-28.05673000",
      "longitude": "-55.12048000"
    },
    {
      "id": 14355,
      "name": "Rosário do Sul",
      "latitude": "-30.25833000",
      "longitude": "-54.91417000"
    },
    {
      "id": 14373,
      "name": "Sagrada Família",
      "latitude": "-27.71478000",
      "longitude": "-53.12850000"
    },
    {
      "id": 14376,
      "name": "Saldanha Marinho",
      "latitude": "-28.38701000",
      "longitude": "-53.09584000"
    },
    {
      "id": 14402,
      "name": "Salto do Jacuí",
      "latitude": "-29.04212000",
      "longitude": "-53.16909000"
    },
    {
      "id": 14405,
      "name": "Salvador das Missões",
      "latitude": "-28.07697000",
      "longitude": "-54.82880000"
    },
    {
      "id": 14406,
      "name": "Salvador do Sul",
      "latitude": "-29.48006000",
      "longitude": "-51.51407000"
    },
    {
      "id": 14410,
      "name": "Sananduva",
      "latitude": "-27.94972000",
      "longitude": "-51.80667000"
    },
    {
      "id": 14416,
      "name": "Sant'Ana do Livramento",
      "latitude": "-30.78069000",
      "longitude": "-55.48158000"
    },
    {
      "id": 14429,
      "name": "Santa Bárbara do Sul",
      "latitude": "-28.37429000",
      "longitude": "-53.25738000"
    },
    {
      "id": 14435,
      "name": "Santa Cecília do Sul",
      "latitude": "-28.17256000",
      "longitude": "-51.92401000"
    },
    {
      "id": 14437,
      "name": "Santa Clara do Sul",
      "latitude": "-29.45575000",
      "longitude": "-52.14362000"
    },
    {
      "id": 14456,
      "name": "Santa Cruz do Sul",
      "latitude": "-29.71750000",
      "longitude": "-52.42583000"
    },
    {
      "id": 14501,
      "name": "Santa Margarida do Sul",
      "latitude": "-30.36744000",
      "longitude": "-54.10999000"
    },
    {
      "id": 14502,
      "name": "Santa Maria",
      "latitude": "-29.68417000",
      "longitude": "-53.80694000"
    },
    {
      "id": 14512,
      "name": "Santa Maria do Herval",
      "latitude": "-29.47954000",
      "longitude": "-50.98806000"
    },
    {
      "id": 14540,
      "name": "Santa Rosa",
      "latitude": "-27.87083000",
      "longitude": "-54.48139000"
    },
    {
      "id": 14553,
      "name": "Santa Tereza",
      "latitude": "-29.15063000",
      "longitude": "-51.72160000"
    },
    {
      "id": 14566,
      "name": "Santa Vitória do Palmar",
      "latitude": "-33.51889000",
      "longitude": "-53.36806000"
    },
    {
      "id": 14570,
      "name": "Santana da Boa Vista",
      "latitude": "-30.76195000",
      "longitude": "-53.18297000"
    },
    {
      "id": 14585,
      "name": "Santana do Livramento",
      "latitude": "-30.89083000",
      "longitude": "-55.53278000"
    },
    {
      "id": 14600,
      "name": "Santiago",
      "latitude": "-29.11368000",
      "longitude": "-54.73359000"
    },
    {
      "id": 14652,
      "name": "Santo Ângelo",
      "latitude": "-28.29917000",
      "longitude": "-54.26306000"
    },
    {
      "id": 14613,
      "name": "Santo Antônio da Patrulha",
      "latitude": "-29.82214000",
      "longitude": "-50.56024000"
    },
    {
      "id": 14615,
      "name": "Santo Antônio das Missões",
      "latitude": "-28.47797000",
      "longitude": "-55.40876000"
    },
    {
      "id": 14634,
      "name": "Santo Antônio do Palma",
      "latitude": "-28.48630000",
      "longitude": "-52.01930000"
    },
    {
      "id": 14637,
      "name": "Santo Antônio do Planalto",
      "latitude": "-28.38607000",
      "longitude": "-52.66579000"
    },
    {
      "id": 14644,
      "name": "Santo Augusto",
      "latitude": "-27.85083000",
      "longitude": "-53.77722000"
    },
    {
      "id": 14645,
      "name": "Santo Cristo",
      "latitude": "-27.78844000",
      "longitude": "-54.70378000"
    },
    {
      "id": 14648,
      "name": "Santo Expedito do Sul",
      "latitude": "-27.92306000",
      "longitude": "-51.67042000"
    },
    {
      "id": 14848,
      "name": "São Borja",
      "latitude": "-28.66056000",
      "longitude": "-56.00444000"
    },
    {
      "id": 14874,
      "name": "São Domingos do Sul",
      "latitude": "-28.54446000",
      "longitude": "-51.87330000"
    },
    {
      "id": 14883,
      "name": "São Francisco de Assis",
      "latitude": "-29.55028000",
      "longitude": "-55.13111000"
    },
    {
      "id": 14887,
      "name": "São Francisco de Paula",
      "latitude": "-29.24246000",
      "longitude": "-50.44928000"
    },
    {
      "id": 14908,
      "name": "São Gabriel",
      "latitude": "-30.33369000",
      "longitude": "-54.33029000"
    },
    {
      "id": 14928,
      "name": "São Jerônimo",
      "latitude": "-29.95917000",
      "longitude": "-51.72222000"
    },
    {
      "id": 15016,
      "name": "São João da Urtiga",
      "latitude": "-27.79677000",
      "longitude": "-51.83882000"
    },
    {
      "id": 15041,
      "name": "São João do Polêsine",
      "latitude": "-29.64559000",
      "longitude": "-53.47291000"
    },
    {
      "id": 14934,
      "name": "São Jorge",
      "latitude": "-28.49890000",
      "longitude": "-51.73076000"
    },
    {
      "id": 14950,
      "name": "São José das Missões",
      "latitude": "-27.79738000",
      "longitude": "-53.12963000"
    },
    {
      "id": 14972,
      "name": "São José do Herval",
      "latitude": "-29.06441000",
      "longitude": "-52.27281000"
    },
    {
      "id": 14973,
      "name": "São José do Hortêncio",
      "latitude": "-29.54364000",
      "longitude": "-51.24977000"
    },
    {
      "id": 14974,
      "name": "São José do Inhacorá",
      "latitude": "-27.73525000",
      "longitude": "-54.12155000"
    },
    {
      "id": 14978,
      "name": "São José do Norte",
      "latitude": "-31.80089000",
      "longitude": "-51.76198000"
    },
    {
      "id": 14979,
      "name": "São José do Ouro",
      "latitude": "-27.75580000",
      "longitude": "-51.55722000"
    },
    {
      "id": 14988,
      "name": "São José do Sul",
      "latitude": "-29.54416000",
      "longitude": "-51.49254000"
    },
    {
      "id": 14991,
      "name": "São José dos Ausentes",
      "latitude": "-28.68307000",
      "longitude": "-49.94674000"
    },
    {
      "id": 15051,
      "name": "São Leopoldo",
      "latitude": "-29.76028000",
      "longitude": "-51.14722000"
    },
    {
      "id": 15057,
      "name": "São Lourenço do Sul",
      "latitude": "-31.36528000",
      "longitude": "-51.97833000"
    },
    {
      "id": 15060,
      "name": "São Luiz Gonzaga",
      "latitude": "-28.40833000",
      "longitude": "-54.96083000"
    },
    {
      "id": 15071,
      "name": "São Marcos",
      "latitude": "-28.96872000",
      "longitude": "-51.04900000"
    },
    {
      "id": 15072,
      "name": "São Martinho",
      "latitude": "-27.72779000",
      "longitude": "-53.96611000"
    },
    {
      "id": 15074,
      "name": "São Martinho da Serra",
      "latitude": "-29.45793000",
      "longitude": "-53.88452000"
    },
    {
      "id": 15083,
      "name": "São Miguel das Missões",
      "latitude": "-28.72430000",
      "longitude": "-54.50818000"
    },
    {
      "id": 15099,
      "name": "São Nicolau",
      "latitude": "-28.22363000",
      "longitude": "-55.25589000"
    },
    {
      "id": 15102,
      "name": "São Paulo das Missões",
      "latitude": "-27.96215000",
      "longitude": "-54.95513000"
    },
    {
      "id": 15110,
      "name": "São Pedro da Serra",
      "latitude": "-29.42131000",
      "longitude": "-51.51442000"
    },
    {
      "id": 15113,
      "name": "São Pedro das Missões",
      "latitude": "-27.79277000",
      "longitude": "-53.24444000"
    },
    {
      "id": 15115,
      "name": "São Pedro do Butiá",
      "latitude": "-28.15561000",
      "longitude": "-54.90336000"
    },
    {
      "id": 15121,
      "name": "São Pedro do Sul",
      "latitude": "-29.62056000",
      "longitude": "-54.17889000"
    },
    {
      "id": 15145,
      "name": "São Sebastião do Caí",
      "latitude": "-29.58667000",
      "longitude": "-51.37556000"
    },
    {
      "id": 15155,
      "name": "São Sepé",
      "latitude": "-30.16056000",
      "longitude": "-53.56528000"
    },
    {
      "id": 15163,
      "name": "São Valentim",
      "latitude": "-27.55106000",
      "longitude": "-52.58722000"
    },
    {
      "id": 15164,
      "name": "São Valentim do Sul",
      "latitude": "-29.06303000",
      "longitude": "-51.73687000"
    },
    {
      "id": 15166,
      "name": "São Valério do Sul",
      "latitude": "-27.81235000",
      "longitude": "-53.92050000"
    },
    {
      "id": 15167,
      "name": "São Vendelino",
      "latitude": "-29.38319000",
      "longitude": "-51.37289000"
    },
    {
      "id": 15174,
      "name": "São Vicente do Sul",
      "latitude": "-29.71725000",
      "longitude": "-54.76241000"
    },
    {
      "id": 14658,
      "name": "Sapiranga",
      "latitude": "-29.63806000",
      "longitude": "-51.00694000"
    },
    {
      "id": 14660,
      "name": "Sapucaia",
      "latitude": "-29.83333000",
      "longitude": "-51.15000000"
    },
    {
      "id": 14663,
      "name": "Sapucaia do Sul",
      "latitude": "-29.81826000",
      "longitude": "-51.15527000"
    },
    {
      "id": 14667,
      "name": "Sarandi",
      "latitude": "-27.94389000",
      "longitude": "-52.92306000"
    },
    {
      "id": 14686,
      "name": "Seberi",
      "latitude": "-27.50884000",
      "longitude": "-53.36482000"
    },
    {
      "id": 14687,
      "name": "Sede Nova",
      "latitude": "-27.64490000",
      "longitude": "-53.96149000"
    },
    {
      "id": 14688,
      "name": "Segredo",
      "latitude": "-29.29705000",
      "longitude": "-52.92281000"
    },
    {
      "id": 14689,
      "name": "Selbach",
      "latitude": "-28.67641000",
      "longitude": "-52.98236000"
    },
    {
      "id": 14707,
      "name": "Senador Salgado Filho",
      "latitude": "-28.02951000",
      "longitude": "-54.52396000"
    },
    {
      "id": 14714,
      "name": "Sentinela do Sul",
      "latitude": "-30.60341000",
      "longitude": "-51.62096000"
    },
    {
      "id": 14716,
      "name": "Serafina Corrêa",
      "latitude": "-28.69115000",
      "longitude": "-51.92671000"
    },
    {
      "id": 15175,
      "name": "Sério",
      "latitude": "-29.40642000",
      "longitude": "-52.24358000"
    },
    {
      "id": 14760,
      "name": "Sertão",
      "latitude": "-28.00412000",
      "longitude": "-52.35664000"
    },
    {
      "id": 14761,
      "name": "Sertão Santana",
      "latitude": "-30.49105000",
      "longitude": "-51.66541000"
    },
    {
      "id": 14767,
      "name": "Sete de Setembro",
      "latitude": "-28.12546000",
      "longitude": "-54.47905000"
    },
    {
      "id": 14770,
      "name": "Severiano de Almeida",
      "latitude": "-27.40649000",
      "longitude": "-52.10747000"
    },
    {
      "id": 14777,
      "name": "Silveira Martins",
      "latitude": "-29.63635000",
      "longitude": "-53.54609000"
    },
    {
      "id": 14790,
      "name": "Sinimbu",
      "latitude": "-29.41512000",
      "longitude": "-52.60499000"
    },
    {
      "id": 14796,
      "name": "Sobradinho",
      "latitude": "-29.41325000",
      "longitude": "-53.02018000"
    },
    {
      "id": 14803,
      "name": "Soledade",
      "latitude": "-28.84047000",
      "longitude": "-52.51015000"
    },
    {
      "id": 15186,
      "name": "Tabaí",
      "latitude": "-29.66719000",
      "longitude": "-51.72796000"
    },
    {
      "id": 15227,
      "name": "Tapejara",
      "latitude": "-28.06426000",
      "longitude": "-52.00823000"
    },
    {
      "id": 15229,
      "name": "Tapera",
      "latitude": "-28.66758000",
      "longitude": "-52.86620000"
    },
    {
      "id": 15232,
      "name": "Tapes",
      "latitude": "-30.67333000",
      "longitude": "-51.39583000"
    },
    {
      "id": 15240,
      "name": "Taquara",
      "latitude": "-29.66336000",
      "longitude": "-50.76365000"
    },
    {
      "id": 15245,
      "name": "Taquari",
      "latitude": "-29.79972000",
      "longitude": "-51.86444000"
    },
    {
      "id": 15251,
      "name": "Taquaruçu do Sul",
      "latitude": "-27.40719000",
      "longitude": "-53.49914000"
    },
    {
      "id": 15263,
      "name": "Tavares",
      "latitude": "-31.27291000",
      "longitude": "-51.07758000"
    },
    {
      "id": 15276,
      "name": "Tenente Portela",
      "latitude": "-27.36291000",
      "longitude": "-53.77115000"
    },
    {
      "id": 15298,
      "name": "Terra de Areia",
      "latitude": "-29.58443000",
      "longitude": "-50.06135000"
    },
    {
      "id": 15300,
      "name": "Teutônia",
      "latitude": "-29.46814000",
      "longitude": "-51.77144000"
    },
    {
      "id": 15320,
      "name": "Tio Hugo",
      "latitude": "-28.58180000",
      "longitude": "-52.59736000"
    },
    {
      "id": 15322,
      "name": "Tiradentes do Sul",
      "latitude": "-27.38183000",
      "longitude": "-54.11303000"
    },
    {
      "id": 15339,
      "name": "Toropi",
      "latitude": "-29.47869000",
      "longitude": "-54.29307000"
    },
    {
      "id": 15341,
      "name": "Torres",
      "latitude": "-29.29667000",
      "longitude": "-49.81982000"
    },
    {
      "id": 15351,
      "name": "Tramandaí",
      "latitude": "-30.03977000",
      "longitude": "-50.23016000"
    },
    {
      "id": 15352,
      "name": "Travesseiro",
      "latitude": "-29.28808000",
      "longitude": "-52.09974000"
    },
    {
      "id": 15369,
      "name": "Três Arroios",
      "latitude": "-27.48222000",
      "longitude": "-52.18370000"
    },
    {
      "id": 15372,
      "name": "Três Cachoeiras",
      "latitude": "-29.47525000",
      "longitude": "-49.98487000"
    },
    {
      "id": 15374,
      "name": "Três Coroas",
      "latitude": "-29.46604000",
      "longitude": "-50.77684000"
    },
    {
      "id": 15384,
      "name": "Três de Maio",
      "latitude": "-27.73449000",
      "longitude": "-54.26018000"
    },
    {
      "id": 15375,
      "name": "Três Forquilhas",
      "latitude": "-29.43246000",
      "longitude": "-50.08341000"
    },
    {
      "id": 15379,
      "name": "Três Palmeiras",
      "latitude": "-27.61276000",
      "longitude": "-52.86635000"
    },
    {
      "id": 15380,
      "name": "Três Passos",
      "latitude": "-27.43083000",
      "longitude": "-53.92238000"
    },
    {
      "id": 15361,
      "name": "Trindade do Sul",
      "latitude": "-27.52679000",
      "longitude": "-52.91351000"
    },
    {
      "id": 15364,
      "name": "Triunfo",
      "latitude": "-29.82246000",
      "longitude": "-51.56027000"
    },
    {
      "id": 15388,
      "name": "Tucunduva",
      "latitude": "-27.64923000",
      "longitude": "-54.43972000"
    },
    {
      "id": 15393,
      "name": "Tunas",
      "latitude": "-29.10586000",
      "longitude": "-52.89867000"
    },
    {
      "id": 15400,
      "name": "Tupanci do Sul",
      "latitude": "-27.92640000",
      "longitude": "-51.54450000"
    },
    {
      "id": 15401,
      "name": "Tupanciretã",
      "latitude": "-29.02190000",
      "longitude": "-53.97471000"
    },
    {
      "id": 15402,
      "name": "Tupandi",
      "latitude": "-29.48000000",
      "longitude": "-51.43044000"
    },
    {
      "id": 15403,
      "name": "Tuparendi",
      "latitude": "-27.68918000",
      "longitude": "-54.55912000"
    },
    {
      "id": 15416,
      "name": "Turuçu",
      "latitude": "-31.52317000",
      "longitude": "-52.12870000"
    },
    {
      "id": 15437,
      "name": "Ubiretama",
      "latitude": "-28.05186000",
      "longitude": "-54.66252000"
    },
    {
      "id": 15458,
      "name": "União da Serra",
      "latitude": "-28.78526000",
      "longitude": "-52.03971000"
    },
    {
      "id": 15455,
      "name": "Unistalda",
      "latitude": "-29.08248000",
      "longitude": "-55.19194000"
    },
    {
      "id": 15479,
      "name": "Uruguaiana",
      "latitude": "-29.82797000",
      "longitude": "-56.63224000"
    },
    {
      "id": 15490,
      "name": "Vacaria",
      "latitude": "-28.41223000",
      "longitude": "-50.94431000"
    },
    {
      "id": 15496,
      "name": "Vale do Sol",
      "latitude": "-29.58160000",
      "longitude": "-52.68161000"
    },
    {
      "id": 15491,
      "name": "Vale Real",
      "latitude": "-29.34986000",
      "longitude": "-51.23013000"
    },
    {
      "id": 15492,
      "name": "Vale Verde",
      "latitude": "-29.83509000",
      "longitude": "-52.10562000"
    },
    {
      "id": 15505,
      "name": "Vanini",
      "latitude": "-28.48831000",
      "longitude": "-51.83316000"
    },
    {
      "id": 15530,
      "name": "Venâncio Aires",
      "latitude": "-29.54206000",
      "longitude": "-52.21959000"
    },
    {
      "id": 15534,
      "name": "Vera Cruz",
      "latitude": "-29.77275000",
      "longitude": "-52.52818000"
    },
    {
      "id": 15538,
      "name": "Veranópolis",
      "latitude": "-28.97791000",
      "longitude": "-51.55656000"
    },
    {
      "id": 15549,
      "name": "Vespasiano Corrêa",
      "latitude": "-29.07064000",
      "longitude": "-51.86646000"
    },
    {
      "id": 15550,
      "name": "Viadutos",
      "latitude": "-27.57743000",
      "longitude": "-51.98735000"
    },
    {
      "id": 15551,
      "name": "Viamão",
      "latitude": "-30.08111000",
      "longitude": "-51.02333000"
    },
    {
      "id": 15555,
      "name": "Vicente Dutra",
      "latitude": "-27.17975000",
      "longitude": "-53.39966000"
    },
    {
      "id": 15558,
      "name": "Victor Graeff",
      "latitude": "-28.54502000",
      "longitude": "-52.68069000"
    },
    {
      "id": 15568,
      "name": "Vila Flores",
      "latitude": "-28.86838000",
      "longitude": "-51.52935000"
    },
    {
      "id": 15569,
      "name": "Vila Lângaro",
      "latitude": "-28.12778000",
      "longitude": "-52.14152000"
    },
    {
      "id": 15570,
      "name": "Vila Maria",
      "latitude": "-28.55505000",
      "longitude": "-52.16380000"
    },
    {
      "id": 15572,
      "name": "Vila Nova do Sul",
      "latitude": "-30.33711000",
      "longitude": "-53.88004000"
    },
    {
      "id": 15589,
      "name": "Vista Alegre",
      "latitude": "-27.31083000",
      "longitude": "-53.51572000"
    },
    {
      "id": 15591,
      "name": "Vista Alegre do Prata",
      "latitude": "-28.83075000",
      "longitude": "-51.79221000"
    },
    {
      "id": 15592,
      "name": "Vista Gaúcha",
      "latitude": "-27.26738000",
      "longitude": "-53.69737000"
    },
    {
      "id": 15600,
      "name": "Vitória das Missões",
      "latitude": "-28.35473000",
      "longitude": "-54.48174000"
    },
    {
      "id": 15631,
      "name": "Westfália",
      "latitude": "-29.42302000",
      "longitude": "-51.75617000"
    },
    {
      "id": 15635,
      "name": "Xangri-lá",
      "latitude": "-29.81049000",
      "longitude": "-50.09223000"
    }
  ],
  "country": {
    "id": 31,
    "name": "Brazil",
    "iso3": "BRA",
    "iso2": "BR",
    "numeric_code": "076",
    "phone_code": "55",
    "capital": "Brasilia",
    "currency": "BRL",
    "currency_name": "Brazilian real",
    "currency_symbol": "R$",
    "tld": ".br",
    "native": "Brasil",
    "region": "Americas",
    "subregion": "South America",
    "timezones": [
      {
        "zoneName": "America/Araguaina",
        "gmtOffset": -10800,
        "gmtOffsetName": "UTC-03:00",
        "abbreviation": "BRT",
        "tzName": "Brasília Time"
      },
      {
        "zoneName": "America/Bahia",
        "gmtOffset": -10800,
        "gmtOffsetName": "UTC-03:00",
        "abbreviation": "BRT",
        "tzName": "Brasília Time"
      },
      {
        "zoneName": "America/Belem",
        "gmtOffset": -10800,
        "gmtOffsetName": "UTC-03:00",
        "abbreviation": "BRT",
        "tzName": "Brasília Time"
      },
      {
        "zoneName": "America/Boa_Vista",
        "gmtOffset": -14400,
        "gmtOffsetName": "UTC-04:00",
        "abbreviation": "AMT",
        "tzName": "Amazon Time (Brazil)[3"
      },
      {
        "zoneName": "America/Campo_Grande",
        "gmtOffset": -14400,
        "gmtOffsetName": "UTC-04:00",
        "abbreviation": "AMT",
        "tzName": "Amazon Time (Brazil)[3"
      },
      {
        "zoneName": "America/Cuiaba",
        "gmtOffset": -14400,
        "gmtOffsetName": "UTC-04:00",
        "abbreviation": "BRT",
        "tzName": "Brasilia Time"
      },
      {
        "zoneName": "America/Eirunepe",
        "gmtOffset": -18000,
        "gmtOffsetName": "UTC-05:00",
        "abbreviation": "ACT",
        "tzName": "Acre Time"
      },
      {
        "zoneName": "America/Fortaleza",
        "gmtOffset": -10800,
        "gmtOffsetName": "UTC-03:00",
        "abbreviation": "BRT",
        "tzName": "Brasília Time"
      },
      {
        "zoneName": "America/Maceio",
        "gmtOffset": -10800,
        "gmtOffsetName": "UTC-03:00",
        "abbreviation": "BRT",
        "tzName": "Brasília Time"
      },
      {
        "zoneName": "America/Manaus",
        "gmtOffset": -14400,
        "gmtOffsetName": "UTC-04:00",
        "abbreviation": "AMT",
        "tzName": "Amazon Time (Brazil)"
      },
      {
        "zoneName": "America/Noronha",
        "gmtOffset": -7200,
        "gmtOffsetName": "UTC-02:00",
        "abbreviation": "FNT",
        "tzName": "Fernando de Noronha Time"
      },
      {
        "zoneName": "America/Porto_Velho",
        "gmtOffset": -14400,
        "gmtOffsetName": "UTC-04:00",
        "abbreviation": "AMT",
        "tzName": "Amazon Time (Brazil)[3"
      },
      {
        "zoneName": "America/Recife",
        "gmtOffset": -10800,
        "gmtOffsetName": "UTC-03:00",
        "abbreviation": "BRT",
        "tzName": "Brasília Time"
      },
      {
        "zoneName": "America/Rio_Branco",
        "gmtOffset": -18000,
        "gmtOffsetName": "UTC-05:00",
        "abbreviation": "ACT",
        "tzName": "Acre Time"
      },
      {
        "zoneName": "America/Santarem",
        "gmtOffset": -10800,
        "gmtOffsetName": "UTC-03:00",
        "abbreviation": "BRT",
        "tzName": "Brasília Time"
      },
      {
        "zoneName": "America/Sao_Paulo",
        "gmtOffset": -10800,
        "gmtOffsetName": "UTC-03:00",
        "abbreviation": "BRT",
        "tzName": "Brasília Time"
      }
    ],
    "translations": {
      "kr": "브라질",
      "pt-BR": "Brasil",
      "pt": "Brasil",
      "nl": "Brazilië",
      "hr": "Brazil",
      "fa": "برزیل",
      "de": "Brasilien",
      "es": "Brasil",
      "fr": "Brésil",
      "ja": "ブラジル",
      "it": "Brasile",
      "cn": "巴西",
      "tr": "Brezilya"
    },
    "latitude": "-10.00000000",
    "longitude": "-55.00000000",
    "emoji": "🇧🇷",
    "emojiU": "U+1F1E7 U+1F1F7"
  }
}