{
  "id": 1363,
  "name": "Benguet",
  "state_code": "BEN",
  "latitude": "16.55772570",
  "longitude": "120.80394740",
  "type": "province",
  "cities": [
    {
      "id": 81148,
      "name": "Adtugan",
      "latitude": "7.81194000",
      "longitude": "124.85444000"
    },
    {
      "id": 81160,
      "name": "Aglayan",
      "latitude": "8.05500000",
      "longitude": "125.13417000"
    },
    {
      "id": 81172,
      "name": "Agusan",
      "latitude": "8.49056000",
      "longitude": "124.73722000"
    },
    {
      "id": 81182,
      "name": "Alae",
      "latitude": "8.42444000",
      "longitude": "124.81278000"
    },
    {
      "id": 81189,
      "name": "Alanib",
      "latitude": "8.02778000",
      "longitude": "124.98611000"
    },
    {
      "id": 81234,
      "name": "Alubijid",
      "latitude": "8.57333000",
      "longitude": "124.47361000"
    },
    {
      "id": 81255,
      "name": "Anakan",
      "latitude": "8.84778000",
      "longitude": "125.15139000"
    },
    {
      "id": 81270,
      "name": "Ani-e",
      "latitude": "8.61361000",
      "longitude": "124.87056000"
    },
    {
      "id": 81296,
      "name": "Aplaya",
      "latitude": "8.60861000",
      "longitude": "124.76806000"
    },
    {
      "id": 81330,
      "name": "Aumbay",
      "latitude": "7.10260000",
      "longitude": "125.78370000"
    },
    {
      "id": 81365,
      "name": "Bacolod",
      "latitude": "8.11667000",
      "longitude": "123.91667000"
    },
    {
      "id": 81389,
      "name": "Bagakay",
      "latitude": "8.14540000",
      "longitude": "123.81570000"
    },
    {
      "id": 81419,
      "name": "Baikingon",
      "latitude": "8.47222000",
      "longitude": "124.55361000"
    },
    {
      "id": 81469,
      "name": "Balila",
      "latitude": "8.00278000",
      "longitude": "125.01306000"
    },
    {
      "id": 81470,
      "name": "Balili",
      "latitude": "7.89500000",
      "longitude": "123.73370000"
    },
    {
      "id": 81475,
      "name": "Balingasag",
      "latitude": "8.74417000",
      "longitude": "124.77694000"
    },
    {
      "id": 81478,
      "name": "Balingoan",
      "latitude": "9.00389000",
      "longitude": "124.85194000"
    },
    {
      "id": 81488,
      "name": "Baliwagan",
      "latitude": "8.71861000",
      "longitude": "124.79056000"
    },
    {
      "id": 81526,
      "name": "Bangahan",
      "latitude": "7.79634000",
      "longitude": "124.73361000"
    },
    {
      "id": 81558,
      "name": "Bantuanon",
      "latitude": "8.01528000",
      "longitude": "125.07083000"
    },
    {
      "id": 81585,
      "name": "Baroy",
      "latitude": "8.02690000",
      "longitude": "123.77840000"
    },
    {
      "id": 81587,
      "name": "Barra",
      "latitude": "8.51028000",
      "longitude": "124.60444000"
    },
    {
      "id": 81593,
      "name": "Basak",
      "latitude": "8.04111000",
      "longitude": "124.86278000"
    },
    {
      "id": 81626,
      "name": "Bato",
      "latitude": "8.60270000",
      "longitude": "123.64490000"
    },
    {
      "id": 81693,
      "name": "Biga",
      "latitude": "8.35778000",
      "longitude": "124.25972000"
    },
    {
      "id": 81722,
      "name": "Binitinan",
      "latitude": "8.71000000",
      "longitude": "124.77556000"
    },
    {
      "id": 81731,
      "name": "Binuangan",
      "latitude": "8.91528000",
      "longitude": "124.78833000"
    },
    {
      "id": 81779,
      "name": "Bolo Bolo",
      "latitude": "8.55833000",
      "longitude": "124.53000000"
    },
    {
      "id": 81785,
      "name": "Bonbon",
      "latitude": "9.10528000",
      "longitude": "124.73389000"
    },
    {
      "id": 81791,
      "name": "Bonifacio",
      "latitude": "8.05250000",
      "longitude": "123.61420000"
    },
    {
      "id": 81799,
      "name": "Boroon",
      "latitude": "8.18278000",
      "longitude": "124.17701000"
    },
    {
      "id": 81845,
      "name": "Bugcaon",
      "latitude": "8.04583000",
      "longitude": "125.11278000"
    },
    {
      "id": 81848,
      "name": "Bugo",
      "latitude": "8.50833000",
      "longitude": "124.75944000"
    },
    {
      "id": 81916,
      "name": "Busdi",
      "latitude": "8.27611000",
      "longitude": "125.25139000"
    },
    {
      "id": 81948,
      "name": "Cabangahan",
      "latitude": "8.02278000",
      "longitude": "125.13750000"
    },
    {
      "id": 81950,
      "name": "Cabanglasan",
      "latitude": "8.12139000",
      "longitude": "125.32750000"
    },
    {
      "id": 81994,
      "name": "Cagayan de Oro",
      "latitude": "8.48222000",
      "longitude": "124.64722000"
    },
    {
      "id": 82011,
      "name": "Calabugao",
      "latitude": "8.45639000",
      "longitude": "125.15889000"
    },
    {
      "id": 82017,
      "name": "Calamba",
      "latitude": "8.55870000",
      "longitude": "123.64250000"
    },
    {
      "id": 82104,
      "name": "Canayan",
      "latitude": "8.19556000",
      "longitude": "125.14472000"
    },
    {
      "id": 82110,
      "name": "Candiis",
      "latitude": "8.97028000",
      "longitude": "125.18417000"
    },
    {
      "id": 82176,
      "name": "Caromatan",
      "latitude": "7.79590000",
      "longitude": "123.71450000"
    },
    {
      "id": 82193,
      "name": "Casisang",
      "latitude": "8.13806000",
      "longitude": "125.12500000"
    },
    {
      "id": 82204,
      "name": "Catarman",
      "latitude": "9.12556000",
      "longitude": "124.67556000"
    },
    {
      "id": 82247,
      "name": "Clarin",
      "latitude": "8.20230000",
      "longitude": "123.85820000"
    },
    {
      "id": 82249,
      "name": "Claveria",
      "latitude": "8.61000000",
      "longitude": "124.89472000"
    },
    {
      "id": 82287,
      "name": "Consuelo",
      "latitude": "8.90167000",
      "longitude": "125.18750000"
    },
    {
      "id": 82301,
      "name": "Cosina",
      "latitude": "8.10611000",
      "longitude": "124.61972000"
    },
    {
      "id": 82338,
      "name": "Dagumba-an",
      "latitude": "8.15306000",
      "longitude": "124.59083000"
    },
    {
      "id": 82350,
      "name": "Dalipuga",
      "latitude": "8.31583000",
      "longitude": "124.25472000"
    },
    {
      "id": 82351,
      "name": "Dalirig",
      "latitude": "8.37722000",
      "longitude": "124.90139000"
    },
    {
      "id": 82352,
      "name": "Dalorong",
      "latitude": "7.58583000",
      "longitude": "125.13278000"
    },
    {
      "id": 82356,
      "name": "Dalwangan",
      "latitude": "8.20056000",
      "longitude": "125.04056000"
    },
    {
      "id": 82361,
      "name": "Damilag",
      "latitude": "8.35472000",
      "longitude": "124.81222000"
    },
    {
      "id": 82365,
      "name": "Damulog",
      "latitude": "7.48361000",
      "longitude": "124.94306000"
    },
    {
      "id": 82367,
      "name": "Dancagan",
      "latitude": "7.60917000",
      "longitude": "125.00417000"
    },
    {
      "id": 82428,
      "name": "Dimaluna",
      "latitude": "8.12180000",
      "longitude": "123.79950000"
    },
    {
      "id": 82431,
      "name": "Dimayon",
      "latitude": "8.06667000",
      "longitude": "124.15000000"
    },
    {
      "id": 82451,
      "name": "Dologon",
      "latitude": "7.84083000",
      "longitude": "125.04444000"
    },
    {
      "id": 82458,
      "name": "Don Carlos",
      "latitude": "7.68000000",
      "longitude": "125.00500000"
    },
    {
      "id": 82464,
      "name": "Dorsalanam",
      "latitude": "8.30667000",
      "longitude": "124.58556000"
    },
    {
      "id": 82484,
      "name": "Dumalaguing",
      "latitude": "8.34694000",
      "longitude": "125.05500000"
    },
    {
      "id": 82507,
      "name": "El Salvador",
      "latitude": "8.56306000",
      "longitude": "124.52250000"
    },
    {
      "id": 82521,
      "name": "Esperanza",
      "latitude": "8.18083000",
      "longitude": "124.00722000"
    },
    {
      "id": 82593,
      "name": "Gimampang",
      "latitude": "8.47139000",
      "longitude": "124.29667000"
    },
    {
      "id": 82598,
      "name": "Gitagum",
      "latitude": "8.59667000",
      "longitude": "124.40639000"
    },
    {
      "id": 82635,
      "name": "Guinisiliban",
      "latitude": "9.09639000",
      "longitude": "124.78278000"
    },
    {
      "id": 82671,
      "name": "Halapitan",
      "latitude": "7.91750000",
      "longitude": "125.33000000"
    },
    {
      "id": 82692,
      "name": "Hinapalanan",
      "latitude": "8.64028000",
      "longitude": "124.87306000"
    },
    {
      "id": 82721,
      "name": "Igpit",
      "latitude": "8.51083000",
      "longitude": "124.58667000"
    },
    {
      "id": 82734,
      "name": "Imbatug",
      "latitude": "8.05444000",
      "longitude": "125.28389000"
    },
    {
      "id": 82735,
      "name": "Imelda",
      "latitude": "7.64703000",
      "longitude": "122.95349000"
    },
    {
      "id": 82737,
      "name": "Impalutao",
      "latitude": "8.25778000",
      "longitude": "125.02750000"
    },
    {
      "id": 82747,
      "name": "Indulang",
      "latitude": "8.09028000",
      "longitude": "124.58444000"
    },
    {
      "id": 82752,
      "name": "Initao",
      "latitude": "8.49972000",
      "longitude": "124.30389000"
    },
    {
      "id": 82753,
      "name": "Inobulan",
      "latitude": "8.88639000",
      "longitude": "124.79472000"
    },
    {
      "id": 82799,
      "name": "Jasaan",
      "latitude": "8.65417000",
      "longitude": "124.75556000"
    },
    {
      "id": 82807,
      "name": "Jimenez",
      "latitude": "8.33650000",
      "longitude": "123.83830000"
    },
    {
      "id": 82822,
      "name": "Kabalantian",
      "latitude": "8.37083000",
      "longitude": "124.32750000"
    },
    {
      "id": 82830,
      "name": "Kabulohan",
      "latitude": "8.04333000",
      "longitude": "125.27667000"
    },
    {
      "id": 82834,
      "name": "Kadingilan",
      "latitude": "7.60111000",
      "longitude": "124.90861000"
    },
    {
      "id": 82843,
      "name": "Kalanganan",
      "latitude": "8.08333000",
      "longitude": "124.24667000"
    },
    {
      "id": 82852,
      "name": "Kalilangan",
      "latitude": "7.74514000",
      "longitude": "124.74777000"
    },
    {
      "id": 82856,
      "name": "Kalugmanan",
      "latitude": "8.27778000",
      "longitude": "124.85972000"
    },
    {
      "id": 82868,
      "name": "Kapatagan",
      "latitude": "7.90030000",
      "longitude": "123.76920000"
    },
    {
      "id": 82886,
      "name": "Kauswagan",
      "latitude": "8.19167000",
      "longitude": "124.08472000"
    },
    {
      "id": 82888,
      "name": "Kawit",
      "latitude": "8.18750000",
      "longitude": "124.06667000"
    },
    {
      "id": 82893,
      "name": "Kibangay",
      "latitude": "8.04972000",
      "longitude": "124.89306000"
    },
    {
      "id": 82894,
      "name": "Kibawe",
      "latitude": "7.56861000",
      "longitude": "124.98778000"
    },
    {
      "id": 82896,
      "name": "Kibonsod",
      "latitude": "9.00694000",
      "longitude": "125.20944000"
    },
    {
      "id": 82898,
      "name": "Kibureau",
      "latitude": "7.69750000",
      "longitude": "125.23250000"
    },
    {
      "id": 82902,
      "name": "Kimanuit",
      "latitude": "7.76039000",
      "longitude": "124.72497000"
    },
    {
      "id": 82903,
      "name": "Kimaya",
      "latitude": "8.56472000",
      "longitude": "124.83972000"
    },
    {
      "id": 82914,
      "name": "Kisolon",
      "latitude": "8.33000000",
      "longitude": "124.97694000"
    },
    {
      "id": 82916,
      "name": "Kitaotao",
      "latitude": "7.63972000",
      "longitude": "125.00889000"
    },
    {
      "id": 82919,
      "name": "Kitobo",
      "latitude": "7.57444000",
      "longitude": "125.10500000"
    },
    {
      "id": 82922,
      "name": "Kolambugan",
      "latitude": "8.11440000",
      "longitude": "123.89710000"
    },
    {
      "id": 82940,
      "name": "La Fortuna",
      "latitude": "8.27972000",
      "longitude": "125.00139000"
    },
    {
      "id": 82952,
      "name": "La Roxas",
      "latitude": "7.86417000",
      "longitude": "124.88694000"
    },
    {
      "id": 82977,
      "name": "Lagindingan",
      "latitude": "8.57472000",
      "longitude": "124.44222000"
    },
    {
      "id": 82978,
      "name": "Lagonglong",
      "latitude": "8.80722000",
      "longitude": "124.79028000"
    },
    {
      "id": 82982,
      "name": "Laguitas",
      "latitude": "8.08917000",
      "longitude": "125.13056000"
    },
    {
      "id": 83013,
      "name": "Langcangan",
      "latitude": "8.47944000",
      "longitude": "123.75583000"
    },
    {
      "id": 83019,
      "name": "Lanipao",
      "latitude": "7.95528000",
      "longitude": "123.77667000"
    },
    {
      "id": 83024,
      "name": "Lantapan",
      "latitude": "7.99778000",
      "longitude": "125.02778000"
    },
    {
      "id": 83030,
      "name": "Lapase",
      "latitude": "8.19240000",
      "longitude": "123.86320000"
    },
    {
      "id": 83035,
      "name": "Lapining",
      "latitude": "7.92270000",
      "longitude": "123.68830000"
    },
    {
      "id": 83087,
      "name": "Libertad",
      "latitude": "8.56111000",
      "longitude": "124.35139000"
    },
    {
      "id": 83095,
      "name": "Libona",
      "latitude": "8.33889000",
      "longitude": "124.73528000"
    },
    {
      "id": 83096,
      "name": "Liboran",
      "latitude": "8.35472000",
      "longitude": "124.64889000"
    },
    {
      "id": 83119,
      "name": "Limbaan",
      "latitude": "7.63960000",
      "longitude": "125.82090000"
    },
    {
      "id": 83128,
      "name": "Linabo",
      "latitude": "8.05417000",
      "longitude": "125.15500000"
    },
    {
      "id": 83131,
      "name": "Linamon",
      "latitude": "8.18603000",
      "longitude": "124.16276000"
    },
    {
      "id": 83138,
      "name": "Lingating",
      "latitude": "8.33167000",
      "longitude": "124.62889000"
    },
    {
      "id": 83141,
      "name": "Lingion",
      "latitude": "8.18806000",
      "longitude": "124.60972000"
    },
    {
      "id": 83151,
      "name": "Little Baguio",
      "latitude": "7.89389000",
      "longitude": "125.27639000"
    },
    {
      "id": 83172,
      "name": "Looc",
      "latitude": "8.84333000",
      "longitude": "124.79167000"
    },
    {
      "id": 83178,
      "name": "Lopez Jaena",
      "latitude": "8.55280000",
      "longitude": "123.76150000"
    },
    {
      "id": 83186,
      "name": "Lourdes",
      "latitude": "8.52500000",
      "longitude": "124.43222000"
    },
    {
      "id": 83205,
      "name": "Lugait",
      "latitude": "8.34111000",
      "longitude": "124.25917000"
    },
    {
      "id": 83222,
      "name": "Lumbayao",
      "latitude": "8.01667000",
      "longitude": "125.16667000"
    },
    {
      "id": 83223,
      "name": "Lumbia",
      "latitude": "8.39583000",
      "longitude": "124.59389000"
    },
    {
      "id": 83235,
      "name": "Lunao",
      "latitude": "8.85028000",
      "longitude": "125.05639000"
    },
    {
      "id": 83247,
      "name": "Lurugan",
      "latitude": "8.01667000",
      "longitude": "124.96667000"
    },
    {
      "id": 83256,
      "name": "Maanas",
      "latitude": "8.89389000",
      "longitude": "125.03083000"
    },
    {
      "id": 83336,
      "name": "Maglamin",
      "latitude": "8.05194000",
      "longitude": "125.26167000"
    },
    {
      "id": 83343,
      "name": "Magsaysay",
      "latitude": "9.02083000",
      "longitude": "125.18250000"
    },
    {
      "id": 83363,
      "name": "Mahinog",
      "latitude": "9.15778000",
      "longitude": "124.78750000"
    },
    {
      "id": 83365,
      "name": "Maigo",
      "latitude": "8.16130000",
      "longitude": "123.95830000"
    },
    {
      "id": 83366,
      "name": "Mailag",
      "latitude": "7.97028000",
      "longitude": "125.13750000"
    },
    {
      "id": 83418,
      "name": "Malaybalay",
      "latitude": "8.15750000",
      "longitude": "125.12778000"
    },
    {
      "id": 83439,
      "name": "Malinaw",
      "latitude": "8.82500000",
      "longitude": "125.19306000"
    },
    {
      "id": 83446,
      "name": "Malitbog",
      "latitude": "8.53389000",
      "longitude": "124.88306000"
    },
    {
      "id": 83459,
      "name": "Maluko",
      "latitude": "8.37500000",
      "longitude": "124.95389000"
    },
    {
      "id": 83472,
      "name": "Mambajao",
      "latitude": "9.25040000",
      "longitude": "124.71560000"
    },
    {
      "id": 83473,
      "name": "Mambatangan",
      "latitude": "8.43333000",
      "longitude": "124.83333000"
    },
    {
      "id": 83474,
      "name": "Mambayaan",
      "latitude": "8.78278000",
      "longitude": "124.78417000"
    },
    {
      "id": 83481,
      "name": "Mamungan",
      "latitude": "8.11722000",
      "longitude": "124.21861000"
    },
    {
      "id": 83485,
      "name": "Managok",
      "latitude": "8.02889000",
      "longitude": "125.18861000"
    },
    {
      "id": 83490,
      "name": "Mananum",
      "latitude": "8.83333000",
      "longitude": "124.95000000"
    },
    {
      "id": 83502,
      "name": "Mandangoa",
      "latitude": "8.77278000",
      "longitude": "124.79111000"
    },
    {
      "id": 83532,
      "name": "Manolo Fortich",
      "latitude": "8.36972000",
      "longitude": "124.86444000"
    },
    {
      "id": 83537,
      "name": "Mantampay",
      "latitude": "8.16667000",
      "longitude": "124.21667000"
    },
    {
      "id": 83539,
      "name": "Manticao",
      "latitude": "8.40417000",
      "longitude": "124.28667000"
    },
    {
      "id": 83557,
      "name": "Maputi",
      "latitude": "8.44972000",
      "longitude": "124.29056000"
    },
    {
      "id": 83561,
      "name": "Maramag",
      "latitude": "7.76333000",
      "longitude": "125.00528000"
    },
    {
      "id": 83562,
      "name": "Maranding",
      "latitude": "7.92480000",
      "longitude": "123.77150000"
    },
    {
      "id": 83575,
      "name": "Maria Cristina",
      "latitude": "8.16604000",
      "longitude": "124.20396000"
    },
    {
      "id": 83576,
      "name": "Mariano",
      "latitude": "8.83333000",
      "longitude": "125.11667000"
    },
    {
      "id": 83610,
      "name": "Mat-i",
      "latitude": "8.40194000",
      "longitude": "124.34528000"
    },
    {
      "id": 83619,
      "name": "Matangad",
      "latitude": "8.57694000",
      "longitude": "124.37000000"
    },
    {
      "id": 83633,
      "name": "Matungao",
      "latitude": "8.13611000",
      "longitude": "124.16417000"
    },
    {
      "id": 83657,
      "name": "Medina",
      "latitude": "8.91222000",
      "longitude": "125.02444000"
    },
    {
      "id": 83668,
      "name": "Miaray",
      "latitude": "7.57472000",
      "longitude": "125.04444000"
    },
    {
      "id": 83686,
      "name": "Minlagas",
      "latitude": "8.87833000",
      "longitude": "125.03889000"
    },
    {
      "id": 83696,
      "name": "Molugan",
      "latitude": "8.53750000",
      "longitude": "124.56222000"
    },
    {
      "id": 83709,
      "name": "Moog",
      "latitude": "8.60111000",
      "longitude": "124.46583000"
    },
    {
      "id": 83723,
      "name": "Munai",
      "latitude": "7.97583000",
      "longitude": "124.06361000"
    },
    {
      "id": 83733,
      "name": "Naawan",
      "latitude": "8.43444000",
      "longitude": "124.28889000"
    },
    {
      "id": 83797,
      "name": "Nañgka",
      "latitude": "8.16667000",
      "longitude": "124.18333000"
    },
    {
      "id": 83776,
      "name": "Napalitan",
      "latitude": "8.77528000",
      "longitude": "124.80222000"
    },
    {
      "id": 83785,
      "name": "Natalungan",
      "latitude": "7.53167000",
      "longitude": "125.02361000"
    },
    {
      "id": 83731,
      "name": "NIA Valencia",
      "latitude": "7.90639000",
      "longitude": "125.09417000"
    },
    {
      "id": 83846,
      "name": "Odiongan",
      "latitude": "8.84583000",
      "longitude": "125.16639000"
    },
    {
      "id": 83855,
      "name": "Opol",
      "latitude": "8.52139000",
      "longitude": "124.57111000"
    },
    {
      "id": 83862,
      "name": "Oroquieta",
      "latitude": "8.48590000",
      "longitude": "123.80480000"
    },
    {
      "id": 83870,
      "name": "Ozamiz City",
      "latitude": "8.14810000",
      "longitude": "123.84050000"
    },
    {
      "id": 83941,
      "name": "Pan-an",
      "latitude": "8.21917000",
      "longitude": "123.84028000"
    },
    {
      "id": 83950,
      "name": "Panalo-on",
      "latitude": "7.91667000",
      "longitude": "123.75000000"
    },
    {
      "id": 83961,
      "name": "Pandan",
      "latitude": "9.23880000",
      "longitude": "124.72780000"
    },
    {
      "id": 83968,
      "name": "Pangabuan",
      "latitude": "8.05694000",
      "longitude": "123.69583000"
    },
    {
      "id": 84000,
      "name": "Pantao-Ragat",
      "latitude": "8.08333000",
      "longitude": "124.13333000"
    },
    {
      "id": 84001,
      "name": "Pantar",
      "latitude": "8.06611000",
      "longitude": "124.25833000"
    },
    {
      "id": 84053,
      "name": "Patrocinio",
      "latitude": "8.61250000",
      "longitude": "124.84556000"
    },
    {
      "id": 84110,
      "name": "Pines",
      "latitude": "8.45222000",
      "longitude": "123.80750000"
    },
    {
      "id": 84134,
      "name": "Plaridel",
      "latitude": "8.62140000",
      "longitude": "123.71010000"
    },
    {
      "id": 84157,
      "name": "Pongol",
      "latitude": "8.27861000",
      "longitude": "124.74833000"
    },
    {
      "id": 84162,
      "name": "Pontian",
      "latitude": "8.28111000",
      "longitude": "124.90028000"
    },
    {
      "id": 84193,
      "name": "Province of Bukidnon",
      "latitude": "8.00000000",
      "longitude": "125.00000000"
    },
    {
      "id": 84198,
      "name": "Province of Camiguin",
      "latitude": "9.16667000",
      "longitude": "124.75000000"
    },
    {
      "id": 84216,
      "name": "Province of Lanao del Norte",
      "latitude": "8.00000000",
      "longitude": "124.00000000"
    },
    {
      "id": 84224,
      "name": "Province of Misamis Occidental",
      "latitude": "8.33333000",
      "longitude": "123.70000000"
    },
    {
      "id": 84225,
      "name": "Province of Misamis Oriental",
      "latitude": "8.75000000",
      "longitude": "125.00000000"
    },
    {
      "id": 84253,
      "name": "Pualas",
      "latitude": "8.01722000",
      "longitude": "123.84806000"
    },
    {
      "id": 84282,
      "name": "Punta Silum",
      "latitude": "8.38167000",
      "longitude": "124.26944000"
    },
    {
      "id": 84296,
      "name": "Quezon",
      "latitude": "7.73028000",
      "longitude": "125.09889000"
    },
    {
      "id": 84333,
      "name": "Rebe",
      "latitude": "7.90760000",
      "longitude": "123.81550000"
    },
    {
      "id": 84386,
      "name": "Sagay",
      "latitude": "9.10590000",
      "longitude": "124.72430000"
    },
    {
      "id": 84402,
      "name": "Salawagan",
      "latitude": "7.70528000",
      "longitude": "125.11500000"
    },
    {
      "id": 84403,
      "name": "Salay",
      "latitude": "8.85917000",
      "longitude": "124.78917000"
    },
    {
      "id": 84409,
      "name": "Salimbalan",
      "latitude": "8.27417000",
      "longitude": "124.72194000"
    },
    {
      "id": 84430,
      "name": "Sampagar",
      "latitude": "7.51389000",
      "longitude": "124.95528000"
    },
    {
      "id": 84460,
      "name": "San Carlos",
      "latitude": "7.95972000",
      "longitude": "125.07750000"
    },
    {
      "id": 84499,
      "name": "San Isidro",
      "latitude": "8.25833000",
      "longitude": "124.59306000"
    },
    {
      "id": 84514,
      "name": "San Jose",
      "latitude": "7.73667000",
      "longitude": "125.07028000"
    },
    {
      "id": 84543,
      "name": "San Luis",
      "latitude": "8.48333000",
      "longitude": "125.00000000"
    },
    {
      "id": 84552,
      "name": "San Martin",
      "latitude": "8.56111000",
      "longitude": "124.77139000"
    },
    {
      "id": 84562,
      "name": "San Miguel",
      "latitude": "8.03000000",
      "longitude": "124.75389000"
    },
    {
      "id": 84619,
      "name": "San Vicente",
      "latitude": "7.65111000",
      "longitude": "125.03444000"
    },
    {
      "id": 84635,
      "name": "Sankanan",
      "latitude": "8.31556000",
      "longitude": "124.85806000"
    },
    {
      "id": 84641,
      "name": "Santa Ana",
      "latitude": "8.51667000",
      "longitude": "124.78333000"
    },
    {
      "id": 84665,
      "name": "Santa Fe",
      "latitude": "8.34250000",
      "longitude": "124.78083000"
    },
    {
      "id": 84744,
      "name": "Sapang Dalaga",
      "latitude": "8.53990000",
      "longitude": "123.56240000"
    },
    {
      "id": 84790,
      "name": "Silae",
      "latitude": "8.15889000",
      "longitude": "125.28250000"
    },
    {
      "id": 84806,
      "name": "Sinacaban",
      "latitude": "8.28640000",
      "longitude": "123.83990000"
    },
    {
      "id": 84819,
      "name": "Sinonoc",
      "latitude": "8.30960000",
      "longitude": "123.84610000"
    },
    {
      "id": 84841,
      "name": "Solana",
      "latitude": "8.62306000",
      "longitude": "124.77056000"
    },
    {
      "id": 84859,
      "name": "Sugbongkogon",
      "latitude": "8.95694000",
      "longitude": "124.79111000"
    },
    {
      "id": 84877,
      "name": "Sumilao",
      "latitude": "8.28722000",
      "longitude": "124.94556000"
    },
    {
      "id": 84879,
      "name": "Sumpong",
      "latitude": "8.16333000",
      "longitude": "125.11833000"
    },
    {
      "id": 84880,
      "name": "Sungai",
      "latitude": "8.45139000",
      "longitude": "124.40278000"
    },
    {
      "id": 84895,
      "name": "Tabid",
      "latitude": "8.10850000",
      "longitude": "123.78010000"
    },
    {
      "id": 84902,
      "name": "Taboc",
      "latitude": "8.87833000",
      "longitude": "124.79750000"
    },
    {
      "id": 84922,
      "name": "Tacub",
      "latitude": "8.18750000",
      "longitude": "124.10806000"
    },
    {
      "id": 84945,
      "name": "Tagoloan",
      "latitude": "8.53954000",
      "longitude": "124.75411000"
    },
    {
      "id": 84968,
      "name": "Talakag",
      "latitude": "8.23361000",
      "longitude": "124.60028000"
    },
    {
      "id": 84985,
      "name": "Talisayan",
      "latitude": "9.00030000",
      "longitude": "124.88091000"
    },
    {
      "id": 85038,
      "name": "Tangub",
      "latitude": "8.06180000",
      "longitude": "123.74770000"
    },
    {
      "id": 85073,
      "name": "Taypano",
      "latitude": "8.37083000",
      "longitude": "124.55944000"
    },
    {
      "id": 85075,
      "name": "Taytay",
      "latitude": "8.54111000",
      "longitude": "124.53972000"
    },
    {
      "id": 85098,
      "name": "Ticala-an",
      "latitude": "8.03528000",
      "longitude": "124.62083000"
    },
    {
      "id": 85109,
      "name": "Tignapalan",
      "latitude": "8.26389000",
      "longitude": "124.57472000"
    },
    {
      "id": 85185,
      "name": "Tubao",
      "latitude": "8.33400000",
      "longitude": "123.85470000"
    },
    {
      "id": 85190,
      "name": "Tubigan",
      "latitude": "8.53222000",
      "longitude": "124.31222000"
    },
    {
      "id": 85196,
      "name": "Tubod",
      "latitude": "8.05550000",
      "longitude": "123.79040000"
    },
    {
      "id": 85204,
      "name": "Tudela",
      "latitude": "8.24720000",
      "longitude": "123.84240000"
    },
    {
      "id": 85230,
      "name": "Tuod",
      "latitude": "8.34333000",
      "longitude": "124.35417000"
    },
    {
      "id": 85233,
      "name": "Tupsan",
      "latitude": "9.19917000",
      "longitude": "124.77694000"
    },
    {
      "id": 85256,
      "name": "Unidos",
      "latitude": "8.59420000",
      "longitude": "123.66800000"
    },
    {
      "id": 85298,
      "name": "Villanueva",
      "latitude": "8.58889000",
      "longitude": "124.77556000"
    },
    {
      "id": 85322,
      "name": "Yumbing",
      "latitude": "9.23930000",
      "longitude": "124.65780000"
    }
  ],
  "country": {
    "id": 174,
    "name": "Philippines",
    "iso3": "PHL",
    "iso2": "PH",
    "numeric_code": "608",
    "phone_code": "63",
    "capital": "Manila",
    "currency": "PHP",
    "currency_name": "Philippine peso",
    "currency_symbol": "₱",
    "tld": ".ph",
    "native": "Pilipinas",
    "region": "Asia",
    "subregion": "South-Eastern Asia",
    "timezones": [
      {
        "zoneName": "Asia/Manila",
        "gmtOffset": 28800,
        "gmtOffsetName": "UTC+08:00",
        "abbreviation": "PHT",
        "tzName": "Philippine Time"
      }
    ],
    "translations": {
      "kr": "필리핀",
      "pt-BR": "Filipinas",
      "pt": "Filipinas",
      "nl": "Filipijnen",
      "hr": "Filipini",
      "fa": "جزایر الندفیلیپین",
      "de": "Philippinen",
      "es": "Filipinas",
      "fr": "Philippines",
      "ja": "フィリピン",
      "it": "Filippine",
      "cn": "菲律宾",
      "tr": "Filipinler"
    },
    "latitude": "13.00000000",
    "longitude": "122.00000000",
    "emoji": "🇵🇭",
    "emojiU": "U+1F1F5 U+1F1ED"
  }
}